Workbook

Sheet Summary
A1: Additional Labs (outside PSSCIVE) - Tools & Equipment with Price
A2: Source: state/central tender lists (NSDC, Delhi CBSE skill subjects, NVS PM SHRI) - these labs are NOT part of the PSSCIVE curriculum. Prices: approximate Indian market rates (Oct 2026, incl. GST) for budget planning only, not quotations. Qty as given in the tender list (1 if blank).
A4: Source | B4: Lab | C4: Sheet | D4: No. of items | E4: Tools & Equipment (INR) | F4: Other Lab Items (INR) | G4: Consumables (INR) | H4: Total (INR) | I4: Total (INR lakh)
A5: NSDC | B5: AI Lab | C5: NSDC-AI | D5: 16 | E5: =SUMIF('NSDC-AI'!$G$5:$G$20,"Tools & Equipment",'NSDC-AI'!$J$5:$J$20) -> 1537500 | F5: =SUMIF('NSDC-AI'!$G$5:$G$20,"Other Lab Items",'NSDC-AI'!$J$5:$J$20) -> 180750 | G5: =SUMIF('NSDC-AI'!$G$5:$G$20,"Consumables",'NSDC-AI'!$J$5:$J$20) -> 1200 | H5: =SUM(E5:G5) -> 1719450 | I5: =ROUND(H5/100000,2) -> 17.19
A6: NSDC | B6: AR-VR Lab | C6: NSDC-ARVR | D6: 20 | E6: =SUMIF('NSDC-ARVR'!$G$5:$G$24,"Tools & Equipment",'NSDC-ARVR'!$J$5:$J$24) -> 676500 | F6: =SUMIF('NSDC-ARVR'!$G$5:$G$24,"Other Lab Items",'NSDC-ARVR'!$J$5:$J$24) -> 312800 | G6: =SUMIF('NSDC-ARVR'!$G$5:$G$24,"Consumables",'NSDC-ARVR'!$J$5:$J$24) -> 0 | H6: =SUM(E6:G6) -> 989300 | I6: =ROUND(H6/100000,2) -> 9.89
A7: NSDC | B7: Financial Markets Management (FMM) Lab | C7: NSDC-FMM | D7: 15 | E7: =SUMIF('NSDC-FMM'!$G$5:$G$19,"Tools & Equipment",'NSDC-FMM'!$J$5:$J$19) -> 558000 | F7: =SUMIF('NSDC-FMM'!$G$5:$G$19,"Other Lab Items",'NSDC-FMM'!$J$5:$J$19) -> 523750 | G7: =SUMIF('NSDC-FMM'!$G$5:$G$19,"Consumables",'NSDC-FMM'!$J$5:$J$19) -> 8200 | H7: =SUM(E7:G7) -> 1089950 | I7: =ROUND(H7/100000,2) -> 10.9
A8: NSDC | B8: Multi Skills Foundation Course (MSFC) Lab | C8: NSDC-MSFC | D8: 272 | E8: =SUMIF('NSDC-MSFC'!$G$5:$G$276,"Tools & Equipment",'NSDC-MSFC'!$J$5:$J$276) -> 237420 | F8: =SUMIF('NSDC-MSFC'!$G$5:$G$276,"Other Lab Items",'NSDC-MSFC'!$J$5:$J$276) -> 126750 | G8: =SUMIF('NSDC-MSFC'!$G$5:$G$276,"Consumables",'NSDC-MSFC'!$J$5:$J$276) -> 12065 | H8: =SUM(E8:G8) -> 376235 | I8: =ROUND(H8/100000,2) -> 3.76
A9: NVS PM SHRI | B9: Multi-Skill Lab | C9: NVS-MSL | D9: 295 | E9: =SUMIF('NVS-MSL'!$G$5:$G$299,"Tools & Equipment",'NVS-MSL'!$J$5:$J$299) -> 320670 | F9: =SUMIF('NVS-MSL'!$G$5:$G$299,"Other Lab Items",'NVS-MSL'!$J$5:$J$299) -> 108850 | G9: =SUMIF('NVS-MSL'!$G$5:$G$299,"Consumables",'NVS-MSL'!$J$5:$J$299) -> 19405 | H9: =SUM(E9:G9) -> 448925 | I9: =ROUND(H9/100000,2) -> 4.49
A10: Delhi CBSE | B10: Multimedia Lab | C10: DL-MM | D10: 8 | E10: =SUMIF('DL-MM'!$G$5:$G$12,"Tools & Equipment",'DL-MM'!$J$5:$J$12) -> 209200 | F10: =SUMIF('DL-MM'!$G$5:$G$12,"Other Lab Items",'DL-MM'!$J$5:$J$12) -> 62500 | G10: =SUMIF('DL-MM'!$G$5:$G$12,"Consumables",'DL-MM'!$J$5:$J$12) -> 0 | H10: =SUM(E10:G10) -> 271700 | I10: =ROUND(H10/100000,2) -> 2.72
A11: Delhi CBSE | B11: Financial Markets Management (FMM) Lab | C11: DL-FMM | D11: 8 | E11: =SUMIF('DL-FMM'!$G$5:$G$12,"Tools & Equipment",'DL-FMM'!$J$5:$J$12) -> 229200 | F11: =SUMIF('DL-FMM'!$G$5:$G$12,"Other Lab Items",'DL-FMM'!$J$5:$J$12) -> 61800 | G11: =SUMIF('DL-FMM'!$G$5:$G$12,"Consumables",'DL-FMM'!$J$5:$J$12) -> 0 | H11: =SUM(E11:G11) -> 291000 | I11: =ROUND(H11/100000,2) -> 2.91
A12: Delhi CBSE | B12: Taxation Lab | C12: DL-TAX | D12: 12 | E12: =SUMIF('DL-TAX'!$G$5:$G$16,"Tools & Equipment",'DL-TAX'!$J$5:$J$16) -> 209200 | F12: =SUMIF('DL-TAX'!$G$5:$G$16,"Other Lab Items",'DL-TAX'!$J$5:$J$16) -> 123000 | G12: =SUMIF('DL-TAX'!$G$5:$G$16,"Consumables",'DL-TAX'!$J$5:$J$16) -> 7500 | H12: =SUM(E12:G12) -> 339700 | I12: =ROUND(H12/100000,2) -> 3.4
A13: Delhi CBSE | B13: Medical Diagnostics Lab | C13: DL-MLT | D13: 40 | E13: =SUMIF('DL-MLT'!$G$5:$G$44,"Tools & Equipment",'DL-MLT'!$J$5:$J$44) -> 285250 | F13: =SUMIF('DL-MLT'!$G$5:$G$44,"Other Lab Items",'DL-MLT'!$J$5:$J$44) -> 5350 | G13: =SUMIF('DL-MLT'!$G$5:$G$44,"Consumables",'DL-MLT'!$J$5:$J$44) -> 107650 | H13: =SUM(E13:G13) -> 398250 | I13: =ROUND(H13/100000,2) -> 3.98
A14: GRAND TOTAL | D14: =SUM(D5:D13) -> 686 | E14: =SUM(E5:E13) -> 4262940 | F14: =SUM(F5:F13) -> 1505550 | G14: =SUM(G5:G13) -> 156020 | H14: =SUM(H5:H13) -> 5924510 | I14: =ROUND(H14/100000,2) -> 59.25
A16: Why these labs are separate: PSSCIVE (NCERT) designs the Samagra Shiksha school vocational curriculum (26 sectors). NSDC runs its own skilling programmes (AI, AR-VR, MSFC labs), Delhi schools follow CBSE skill subjects (FMM, Taxation, Medical Diagnostics, Multimedia) and NVS PM SHRI has its own Multi-Skill Lab spec.
A17: Prepared by - Subodh Kumar

Sheet NSDC-AI
A1: NSDC - AI Lab
A2: Source: state/central tender lists (NSDC, Delhi CBSE skill subjects, NVS PM SHRI) - these labs are NOT part of the PSSCIVE curriculum. Prices: approximate Indian market rates (Oct 2026, incl. GST) for budget planning only, not quotations. Qty as given in the tender list (1 if blank).
A4: S.No | B4: Section | C4: Item | D4: Specification (as in tender) | E4: Qty (as in list) | F4: Qty | G4: Type | H4: Unit | I4: Approx. Unit Price (INR) | J4: Amount (INR) | K4: Visual
A5: 1 | B5: - | C5: Desktop computers | D5: Processor :Intel Core i5-1235U or Equivalent, upto 4.4 GHz frequency, 10 Cores, 12 Threads, Chipset :Intel Integrated SoC or Equivalent RAM Size (GB) : 8 GB DDR4-2933 MHz RAM (1 x 8 GB), Hard Disk (GB) : 512 GB PCIe® NVMe™ M.2 SSD, Operating System (Pre-Loaded): Windows 11 Home or Equivalent, USB Port 3.0(No.) :1 or more, USB Port 2.0 (No.):1 or more, Network Connectivity :10/100/1000 on board integrated gigabit port, Display: 35.6 cm (14 inch) diagonal, HD (1366 x 768), micro-edge, BrightView, 250 nits, 45% NTSC, Monitor Size (INCHES): 35.6 cm (14) diagonal HD display or higher Warranty (Year) : 1 year (1/1/1) limited warranty includes 1 year of parts and labour. On-site repair. Keyboard: Full-size, jet black keyboard, Pointing Device: Image pad with multi-touch gesture support; Precision Touchpad Support, Wireless: Realtek RTL8821CE-M 802.11a/b/g/n/ac (1x1) Wi- Fi® and Bluetooth® 4.2 combo or Equivalent, Power Supply: 65 W Smart AC power adapter, Battery Type: 3-cell, 41 Wh Li-ion, Energy Efficiency Compliance: EPEAT® registered | E5: 15 | F5: 15 | G5: Tools & Equipment | H5: pcs | I5: 55000 | J5: =F5*I5 -> 825000 | K5: Click here
A6: 2 | B6: - | C6: Intel Brand or Equivalent Learning Kit | D6: Plug-n-Play boards pre-loaded with software supporting AI modelling and deployment, IoT, 3D printing and more | E6: 15 | F6: 15 | G6: Tools & Equipment | H6: kit | I6: 25000 | J6: =F6*I6 -> 375000 | K6: Click here
A7: 3 | B7: - | C7: Printer/Scanner/Xerox | D7: Brand: HP/Canon Pixma or Equivalent All-In-One Colour Inkjet Printer (Black). Copy,Print,Scan, 16 Mb internal memory. Up to 46 db. Noise level. Output Tray capacity 50 pages. Media Size Supported A4, A5, B5, Letter, Legal, Envelopes, Custom size. Input Tray capacity 100. USB support-Yes. Warranty Period 1 Year 1. Spill-free replenishment system. 2. Operation System : Windows. 3. Print up to 8000 pages with a set of colour ink bottle; Print up to 5000 with a set of black ink bottle. 4. Create borderless brochures, flyers, photos and other documents. | E7: 1 | F7: 1 | G7: Tools & Equipment | H7: unit | I7: 18000 | J7: =F7*I7 -> 18000 | K7: Click here
A8: 4 | B8: - | C8: Local Area Network | D8: 16 port Network switch. 16-Port 10/100Mbps Desktop/Rackmount Switch, Power Cord, Installation Guide, Rackmount Kit and Rubber Feet. 110 Volts. 801.11ac. Auto-MDIX, IEEE 802.3, Ethernet, Auto-MDI, Fast Ethernet | E8: 1 | F8: 1 | G8: Other Lab Items | H8: unit | I8: 4500 | J8: =F8*I8 -> 4500 | K8: Click here
A9: 5 | B9: - | C9: Lab Chairs | D9: Stackable chairs with arms, Dimensions: length 17, width: 17, height:32 (in inches). Material: Polypropylene | E9: 15 | F9: 15 | G9: Other Lab Items | H9: unit | I9: 1800 | J9: =F9*I9 -> 27000 | K9: Click here
A10: 6 | B10: - | C10: Computer Tables | D10: Table height :80 CMS, length :70 cms, width :45 cms with key board and CPU shelves Material - Wooden | E10: 15 | F10: 15 | G10: Tools & Equipment | H10: pcs | I10: 8500 | J10: =F10*I10 -> 127500 | K10: Click here
A11: 7 | B11: - | C11: White Board | D11: Material of Board Ceramic Steel Material of Frame Anodized extruded Aluminium alloy hollow section of designation 63400 conforming to IS: 1285 Material of Back Cover Galvanized steel sheets conforming to IS:277 Thickness and Material of back support (conforming to IS:12406) 9 millimetre | E11: 1 | F11: 1 | G11: Other Lab Items | H11: pcs | I11: 3500 | J11: =F11*I11 -> 3500 | K11: Click here
A12: 8 | B12: - | C12: Demonstration Charts | D12: 4" X 3" Ft. | E12: 5 | F12: 5 | G12: Other Lab Items | H12: set | I12: 850 | J12: =F12*I12 -> 4250 | K12: Click here
A13: 9 | B13: - | C13: USB / Pen drive | D13: Capacity = 8GB each USB | E13: 2 | F13: 2 | G13: Consumables | H13: unit | I13: 350 | J13: =F13*I13 -> 700 | K13: Click here
A14: 10 | B14: - | C14: RJ45 connecters | D14: Connector used in Ethernet and other data links & cables | E14: 1 | F14: 1 | G14: Consumables | H14: pack of 100 | I14: 500 | J14: =F14*I14 -> 500 | K14: Click here
A15: 11 | B15: - | C15: Anti Virus software | D15: One license for one laptop computer therefore 15 licenses for 15 computers | E15: 15 | F15: 15 | G15: Other Lab Items | H15: unit | I15: 1200 | J15: =F15*I15 -> 18000 | K15: Click here
A16: 12 | B16: - | C16: Printer Cartridges (Compatible Printer Type Required) | D16: GI-790 / HP 3052 PRINTER CATRIDGE 12A (hp) , Brand HP or Equivalent Type of Cartridge/Consumable Toner Ink/Toner/Drum Model number HP 3052 PRINTER CATRIDGE 12A or Equivalent Corresponding Part number/ code HP 3052 PRINTER CATRIDGE 12A or Equivalent | E16: 1 | F16: 1 | G16: Tools & Equipment | H16: unit | I16: 3500 | J16: =F16*I16 -> 3500 | K16: Click here
... A20: 16 | B20: - | C20: Smart Board | D20: Panel: Diagonal Size & Resolution-65" or Higher, UHD 3840 × 2160 pixels Light life-50,000 hrs or higher Brightness-400 nits or Higher : Touch screen: Touch technology & Touch Points-Infrared touch, 20 points or Higher Touch response time & Accuracy- < 8 ms or faster, ±1.0 mm or better : Inbuilt Configuration: CPU & Speed- Quad-core A73+ Quad-core A53 or later,2.2 GHz or Higher OS- Android 11.0 or later Memory RAM- 8GB or Higher Memory Storage- 128 GB or Higher : Connectivity: I/O Ports- 1 x VGA, 3 × HDMI 2.0 IN & 1 × HDMI 2.0,Out port, 1 x DP, USB 2.0 × 2 + 3.0 × 2,USB -B x 2, 1 x USB C port, SPDIF x 1,RS232 x 1, LAN Port x 1 : Audio Configuration: Microphone-8 or more Speaker, Subwoofer- 2 × 16 W Speaker & 1 x 16 W Subwoofer : Built-in: Functionalities-PM2.5 Particle sensor, Temperature,Humidity, Air, Motion Sensor, Flicker Free, Low Blue Light Connectivity-Bluetooth, WI Fi, NFC : Software: Functionalities: White Boarding, Wireless Screen Sharing,Quick Access Tool | E20: 1 | F20: 1 | G20: Tools & Equipment | H20: pcs | I20: 180000 | J20: =F20*I20 -> 180000 | K20: Click here
C21: TOTAL (approx.) | J21: =SUM(J5:J20) -> 1719450
A23: Prepared by - Subodh Kumar

Sheet NSDC-ARVR
A1: NSDC - AR-VR Lab
A2: Source: state/central tender lists (NSDC, Delhi CBSE skill subjects, NVS PM SHRI) - these labs are NOT part of the PSSCIVE curriculum. Prices: approximate Indian market rates (Oct 2026, incl. GST) for budget planning only, not quotations. Qty as given in the tender list (1 if blank).
A4: S.No | B4: Section | C4: Item | D4: Specification (as in tender) | E4: Qty (as in list) | F4: Qty | G4: Type | H4: Unit | I4: Approx. Unit Price (INR) | J4: Amount (INR) | K4: Visual
A5: 1 | B5: - | C5: VR Standalone Headset | D5: Headset: 191.5 mm x 102 mm x 142.5 mm (295.5 mm with fully-unfolded strap), 503g; Color: white. Controllers: 90 x 120mm (per controller, including tracking ring with IR LED-based tracking), 126g (per controller, without battery), around 147g (with a AA battery); Around 30 hours of usage from one AA battery; Color: white. Display: IPS LCD, 1832x1920px per year resolution, 90Hz native refresh rate (currently capable of 72Hz, 90Hz coming with software update); around 90-degree field of view (estimated); adjustable IPD - three-position slider - 58mm, 63mm and 68mm Chipset: Qualcomm Snapdragon XR2 (7 nm): Octa- core (1x2.84 GHz Kryo 585 & 3x2.42 GHz Kryo 585 & 4x1.8 GHz Kryo 585); Adreno 650. Memory: 64/256GB 6GB LPDDR5 RAM. OS/Software: based on Android 10, no Google Play Services, uses proprietary store for apps and games; Supports playing PC VR games through link and third-party wireless solutions. Tracking: Supports 6 degrees of freedom (6DoF) head and hand tracking through integrated Insight technology (inside-out tracking); 4 front-facing cameras for visual controller tracking, plus gyroscopes and accelerometers in headset and controllers; Hand tracking (beta). Play space: Stationary and room-scale support, up to around 20m x 20m play area is mappable. Headset Battery: 3,640 mAh (14.0 Wh) lithium-ion (2 to 3 hours of use on a single charge); 10W (5V@2A) charging (around 2.5 hours for a full charge). Audio: Built-in stereo speakers and microphone, 3.5mm audio jack, support for 3D audio. Connectivity: Wi-Fi b/g/n/ac(5)/ax(6), 60 GHz Wi-Fi ay module (currently not in use); Bluetooth 5.0 LE; Type-C USB port, with USB Host support; 3.5mm audio jack. | E5: 10 | F5: 10 | G5: Tools & Equipment | H5: unit | I5: 35000 | J5: =F5*I5 -> 350000 | K5: Click here
A6: 2 | B6: - | C6: Tablets | D6: 10.1" HD (1280x800) display with 400 nits' brightness 3GB RAM, 32GB ROM expandable up to 256 GB, ex-FAT up to 1 TB Octa-core processor with 2.3GHz frequency 8 MP Rear Camera, 5 MP front camera | E6: 10 | F6: 10 | G6: Tools & Equipment | H6: unit | I6: 12000 | J6: =F6*I6 -> 120000 | K6: Click here
A7: 3 | B7: - | C7: Headphones | D7: Headphone with 3.5mm Jack | E7: 10 | F7: 10 | G7: Tools & Equipment | H7: pcs | I7: 4500 | J7: =F7*I7 -> 45000 | K7: Click here
A8: 4 | B8: - | C8: AR Globe Kit | D8: AR Globe Kit for Education Purposes | E8: 10 | F8: 10 | G8: Tools & Equipment | H8: kit | I8: 3500 | J8: =F8*I8 -> 35000 | K8: Click here
A9: 5 | B9: - | C9: AR Cubes-based | D9: AR Cube for Educational Experiences | E9: 10 | F9: 10 | G9: Tools & Equipment | H9: kit | I9: 2500 | J9: =F9*I9 -> 25000 | K9: Click here
A10: 6 | B10: - | C10: Laptop for Teacher | D10: Intel i5 or Equivalent Gen 11+ Processor OR Ryzen 3 3250U+ Processor 16GB RAM 256GB SSD Windows 11 or Equivalent MS Office or Equivalent Office Installed Programming Software Installed 1 Year Extended Warranty | E10: 1 | F10: 1 | G10: Tools & Equipment | H10: unit | I10: 55000 | J10: =F10*I10 -> 55000 | K10: Click here
A11: 7 | B11: - | C11: Projector | D11: Smart LED Projector with WiFi/BT v5.1, FHD 1080p, Apps, Miracast DLNA/Airplay Support, 5000 Lumen, 30000H lifespan, HDMI, 2X USB Speaker and Remote Control | E11: 1 | F11: 1 | G11: Tools & Equipment | H11: pcs | I11: 45000 | J11: =F11*I11 -> 45000 | K11: Click here
A12: 8 | B12: - | C12: Projector Mounting Kit | D12: Compatible with Projector | E12: 1 | F12: 1 | G12: Tools & Equipment | H12: unit | I12: 1500 | J12: =F12*I12 -> 1500 | K12: Click here
A13: 9 | B13: - | C13: Gaming Chair for Virtual Reality Laboratory | D13: lumbar support and headrest to accommodate extended usage. Material: High-quality, durable fabric or leather with breathable properties Adjustability: Features should include height adjustment, tilt mechanism, and 360-degree swivel capability. Armrests: Adjustable armrests to support various user activities and preferences. Base and Mobility: Sturdy base with smooth- rolling casters suitable for various floor types. Load Capacity: Must support a minimum weight capacity of 120kg. Compatibility: Should be designed to enhance the virtual reality experience, providing comfort and stability during use. | E13: 10 | F13: 10 | G13: Other Lab Items | H13: unit | I13: 9000 | J13: =F13*I13 -> 90000 | K13: Click here
A14: 10 | B14: - | C14: Activity Table | D14: Designed to connect with Chair/Sofa/Recliner and should have storage capacity for VR Headset, Books, Headphone, Tablet | E14: 10 | F14: 10 | G14: Other Lab Items | H14: unit | I14: 4500 | J14: =F14*I14 -> 45000 | K14: Click here
A15: 11 | B15: - | C15: Teacher Table | D15: 5 x 2 Ft with Drawers | E15: 1 | F15: 1 | G15: Other Lab Items | H15: unit | I15: 9000 | J15: =F15*I15 -> 9000 | K15: Click here
A16: 12 | B16: - | C16: Cupboard | D16: Metallic/Wooden with glass doors, W36XD18XH48 inch | E16: 2 | F16: 2 | G16: Other Lab Items | H16: pcs | I16: 8500 | J16: =F16*I16 -> 17000 | K16: Click here
... A24: 20 | B24: - | C24: Software and Content for Students | D24: Oil and Gas Sector Processes for Oil & Gas Terminal, Retail and LPG Bottling Plants For 3 Years | E24: 1 | F24: 1 | G24: Other Lab Items | H24: licence | I24: 75000 | J24: =F24*I24 -> 75000 | K24: Click here
C25: TOTAL (approx.) | J25: =SUM(J5:J24) -> 989300
A27: Prepared by - Subodh Kumar

Sheet NSDC-FMM
A1: NSDC - Financial Markets Management (FMM) Lab
A2: Source: state/central tender lists (NSDC, Delhi CBSE skill subjects, NVS PM SHRI) - these labs are NOT part of the PSSCIVE curriculum. Prices: approximate Indian market rates (Oct 2026, incl. GST) for budget planning only, not quotations. Qty as given in the tender list (1 if blank).
A4: S.No | B4: Section | C4: Item | D4: Specification (as in tender) | E4: Qty (as in list) | F4: Qty | G4: Type | H4: Unit | I4: Approx. Unit Price (INR) | J4: Amount (INR) | K4: Visual
A5: 1 | B5: - | C5: Desktop Computer | D5: Processor :Intel Pentium Silver N6000 or equivalent, 3.3GHz burst frequency, 4MB L3 Cache, 4 Cores, 4 Threads Chipset :Intel Integrated SoC or equivalent RAM Size (GB) : 8 GB DDR4-2933 MHz RAM (1 x 8 GB) Hard Disk (GB) : 256 GB PCIe® NVMe™ M.2 SSD Operating System (Pre-Loaded): Windows 11 Home or equivalent USB Port 3.0(No.) :1 or more USB Port 2.0 (No.):1 or more Network Connectivity :10/100/1000 on board integrated gigabit port Display: 35.6 cm (14) diagonal, HD (1366 x 768), micro-edge, BrightView, 250 nits, 45% NTSC Monitor Size (INCHES): 35.6 cm (14) diagonal HD display Warranty (Year) : 1 year (1/1/1) limited warranty includes 1 year of parts and labour. On-site repair. Keyboard: Full-size, jet black keyboard Pointing Device: Image pad with multi-touch gesture support; Precision Touchpad Support Wireless: Realtek or Equivalent RTL8821CE-M 802.11a/b/g/n/ac (1x1) Wi-Fi® and Bluetooth® 4.2 combo Power Supply: 65 W Smart AC power adapter Battery Type: 3-cell, 41 Wh Li-ion Energy Efficiency Compliance: EPEAT® registered | E5: 12 | F5: 12 | G5: Tools & Equipment | H5: pcs | I5: 45000 | J5: =F5*I5 -> 540000 | K5: Click here
A6: 2 | B6: - | C6: Printer/Scanner/Xerox | D6: Brand: HP/Canon Pixma or Equivalent All-In-One Colour Inkjet Printer (Black). Copy,Print,Scan, 16 Mb internal memory. Up to 46 db. Noise level. Output Tray capacity 50 pages. Media Size Supported A4, A5, B5, Letter, Legal, Envelopes, Custom size. Input Tray capacity 100. USB support-Yes. Warranty Period 1 Year 1. Spill-free replenishment system. 2. Operation System : Windows or equivalent. 3. Print up to 8000 pages with a set of colour ink bottle; Print up to 5000 with a set of black ink bottle. 4. Create borderless brochures, flyers, photos and other documents. | E6: 1 | F6: 1 | G6: Tools & Equipment | H6: unit | I6: 18000 | J6: =F6*I6 -> 18000 | K6: Click here
A7: 3 | B7: - | C7: Local Area Network | D7: 16 port Network switch. 16-Port 10/100Mbps Desktop/Rackmount Switch, Power Cord, Installation Guide, Rackmount Kit and Rubber Feet. 110 Volts. 801.11ac. Auto-MDIX, IEEE 802.3, Ethernet, Auto-MDI, Fast Ethernet | E7: 1 | F7: 1 | G7: Other Lab Items | H7: unit | I7: 4500 | J7: =F7*I7 -> 4500 | K7: Click here
A8: 4 | B8: - | C8: Lab Chairs | D8: Stackable chairs with arms, Dimensions: length 17, width: 17, height:32 (in inches). Material: Polypropylene | E8: 30 | F8: 30 | G8: Other Lab Items | H8: unit | I8: 1800 | J8: =F8*I8 -> 54000 | K8: Click here
A9: 5 | B9: - | C9: Computer Tables | D9: Table height :80 CMS, length :70 cms, width :45 cms with key board and CPU shelves | E9: 15 | F9: 15 | G9: Other Lab Items | H9: pcs | I9: 8500 | J9: =F9*I9 -> 127500 | K9: Click here
A10: 6 | B10: - | C10: White Board | D10: Material of Board Ceramic Steel Material of Frame Anodized extruded Aluminium alloy hollow section of designation 63400 conforming to IS: 1285 Material of Back Cover Galvanized steel sheets conforming to IS:277 Thickness and Material of back support (conforming to IS:12406) 9 millimetre | E10: 1 | F10: 1 | G10: Other Lab Items | H10: pcs | I10: 3500 | J10: =F10*I10 -> 3500 | K10: Click here
A11: 7 | B11: - | C11: Demonstration Charts | D11: 4" X 3" Ft. | E11: 5 | F11: 5 | G11: Other Lab Items | H11: set | I11: 850 | J11: =F11*I11 -> 4250 | K11: Click here
A12: 8 | B12: - | C12: USB / Pen drive | D12: Capacity = 8GB each USB | E12: 2 | F12: 2 | G12: Consumables | H12: unit | I12: 350 | J12: =F12*I12 -> 700 | K12: Click here
A13: 9 | B13: - | C13: RJ45 connecters | D13: Connector used in Ethernet and other data links & cables | E13: 1 | F13: 1 | G13: Consumables | H13: pack of 100 | I13: 500 | J13: =F13*I13 -> 500 | K13: Click here
A14: 10 | B14: - | C14: Anti Virus software | D14: One license for one laptop computer therefore 15 licenses for 15 computers | E14: 15 | F14: 15 | G14: Other Lab Items | H14: unit | I14: 1200 | J14: =F14*I14 -> 18000 | K14: Click here
A15: 11 | B15: - | C15: Printer Cartridges (Compatible Printer Type Required) | D15: GI-790 / HP 3052 PRINTER CATRIDGE 12A (hp) , Brand HP or Equivalent Type of Cartridge/Consumable Toner Ink/Toner/Drum Model number HP 3052 PRINTER CATRIDGE 12A or equivalent Corresponding Part number/ code HP 3052 PRINTER CATRIDGE 12A or equivalent | E15: 2 | F15: 2 | G15: Consumables | H15: unit | I15: 3500 | J15: =F15*I15 -> 7000 | K15: Click here
A16: 12 | B16: - | C16: Fire extinguisher | D16: Type Stored Pressure Extinguishing Media Powder Based Expellant Medium N2 Based (Stored Pressure) Foam Based Fire Extinguisher Capacity(Litres) 4 Powder Based Fire Extinguisher Capacity (Kg) 4 Carbon Dioxide Based Fire Extinguisher Capacity (Kg) 4.5 | E16: 1 | F16: 1 | G16: Other Lab Items | H16: pcs | I16: 3500 | J16: =F16*I16 -> 3500 | K16: Click here
... A19: 15 | B19: - | C19: Smart Board | D19: Panel: Diagonal Size & Resolution-65" or Higher, UHD 3840 × 2160 pixels Light life-50,000 hrs or higher Brightness-400 nits or Higher : Touch screen: Touch technology & Touch Points-Infrared touch, 20 points or Higher Touch response time & Accuracy- < 8 ms or faster, ±1.0 mm or better : Inbuilt Configuration: CPU & Speed- Quad-core A73+ Quad-core A53 or later,2.2 GHz or Higher OS- Android 11.0 or later Memory RAM- 8GB or Higher Memory Storage- 128 GB or Higher : Connectivity: I/O Ports- 1 x VGA, 3 × HDMI 2.0 IN & 1 × HDMI 2.0,Out port, 1 x DP, USB 2.0 × 2 + 3.0 × 2,USB -B x 2, 1 x USB C port, SPDIF x 1,RS232 x 1, LAN Port x 1 : Audio Configuration: Microphone-8 or more Speaker, Subwoofer- 2 × 16 W Speaker & 1 x 16 W Subwoofer : Built-in: Functionalities-PM2.5 Particle sensor, Temperature,Humidity, Air, Motion Sensor, Flicker Free, Low Blue Light Connectivity-Bluetooth, WI Fi, NFC : Software: Functionalities: White Boarding, Wireless Screen Sharing,Quick Access Tool | E19: 1 | F19: 1 | G19: Other Lab Items | H19: pcs | I19: 180000 | J19: =F19*I19 -> 180000 | K19: Click here
C20: TOTAL (approx.) | J20: =SUM(J5:J19) -> 1089950
A22: Prepared by - Subodh Kumar

Sheet NSDC-MSFC
A1: NSDC - Multi Skills Foundation Course (MSFC) Lab
A2: Source: state/central tender lists (NSDC, Delhi CBSE skill subjects, NVS PM SHRI) - these labs are NOT part of the PSSCIVE curriculum. Prices: approximate Indian market rates (Oct 2026, incl. GST) for budget planning only, not quotations. Qty as given in the tender list (1 if blank).
A4: S.No | B4: Section | C4: Item | D4: Specification (as in tender) | E4: Qty (as in list) | F4: Qty | G4: Type | H4: Unit | I4: Approx. Unit Price (INR) | J4: Amount (INR) | K4: Visual
A5: 1 | B5: Workshop & Engineering Techniques | C5: Steel Ruler | D5: 150 mm, 300mm ,1 mtr | E5: 2 | F5: 2 | G5: Tools & Equipment | H5: set | I5: 450 | J5: =F5*I5 -> 900 | K5: Click here
A6: 2 | B6: Workshop & Engineering Techniques | C6: Measuring Tape | D6: 3 and 5 Meter | E6: 2 | F6: 2 | G6: Tools & Equipment | H6: pcs | I6: 250 | J6: =F6*I6 -> 500 | K6: Click here
A7: 3 | B7: Workshop & Engineering Techniques | C7: Spirit Level Bottle | D7: 0.01 - 0.05mm/met er | E7: 1 | F7: 1 | G7: Tools & Equipment | H7: unit | I7: 350 | J7: =F7*I7 -> 350 | K7: Click here
A8: 4 | B8: Workshop & Engineering Techniques | C8: Vernier Caliper | D8: 150mm (LC/0.02mm) & 200mm (LC/0.05mm) | E8: 1 | F8: 1 | G8: Tools & Equipment | H8: pcs | I8: 1200 | J8: =F8*I8 -> 1200 | K8: Click here
A9: 5 | B9: Workshop & Engineering Techniques | C9: Vernier Caliper- Digital | D9: 150mm Zhart or (LC/0.02mm) equivalent & 200mm (LC/0.05mm) | E9: 1 | F9: 1 | G9: Tools & Equipment | H9: unit | I9: 2500 | J9: =F9*I9 -> 2500 | K9: Click here
A10: 6 | B10: Workshop & Engineering Techniques | C10: Spring Caliper Inside /Outside /Divider | D10: 6" or 150 mm Length Inside /Outside /Divider | E10: 2 | F10: 2 | G10: Tools & Equipment | H10: set | I10: 600 | J10: =F10*I10 -> 1200 | K10: Click here
A11: 7 | B11: Workshop & Engineering Techniques | C11: Out - Side Micromet er | D11: 0-25mm (LC/0.01mm) | E11: 1 | F11: 1 | G11: Tools & Equipment | H11: unit | I11: 1800 | J11: =F11*I11 -> 1800 | K11: Click here
A12: 8 | B12: Workshop & Engineering Techniques | C12: Out - Side Micromet er Digital | D12: 0-25mm (LC/0.01mm) | E12: 1 | F12: 1 | G12: Tools & Equipment | H12: unit | I12: 4500 | J12: =F12*I12 -> 4500 | K12: Click here
A13: 9 | B13: Workshop & Engineering Techniques | C13: Threading Gauge ( Engineerin g) | D13: Metric | E13: 2 | F13: 2 | G13: Tools & Equipment | H13: unit | I13: 350 | J13: =F13*I13 -> 700 | K13: Click here
A14: 10 | B14: Workshop & Engineering Techniques | C14: Threading Gauge ( Plumbing) | D14: British | E14: 2 | F14: 2 | G14: Tools & Equipment | H14: unit | I14: 350 | J14: =F14*I14 -> 700 | K14: Click here
A15: 11 | B15: Workshop & Engineering Techniques | C15: Radius Gauge | D15: Metric | E15: 2 | F15: 2 | G15: Tools & Equipment | H15: set | I15: 450 | J15: =F15*I15 -> 900 | K15: Click here
A16: 12 | B16: Workshop & Engineering Techniques | C16: Try Square | D16: 75mmx100m m | E16: 1 | F16: 1 | G16: Tools & Equipment | H16: unit | I16: 250 | J16: =F16*I16 -> 250 | K16: Click here
... A276: 272 | B276: Section Name Plates / Branding Boards | C276: Display Corner | D276: Dimensions: 1x0.33 sq.ft | E276: 1 | F276: 1 | G276: Other Lab Items | H276: unit | I276: 250 | J276: =F276*I276 -> 250 | K276: Click here
C277: TOTAL (approx.) | J277: =SUM(J5:J276) -> 376235
A279: Prepared by - Subodh Kumar

Sheet NVS-MSL
A1: NVS PM SHRI - Multi-Skill Lab
A2: Source: state/central tender lists (NSDC, Delhi CBSE skill subjects, NVS PM SHRI) - these labs are NOT part of the PSSCIVE curriculum. Prices: approximate Indian market rates (Oct 2026, incl. GST) for budget planning only, not quotations. Qty as given in the tender list (1 if blank).
A4: S.No | B4: Section | C4: Item | D4: Specification (as in tender) | E4: Qty (as in list) | F4: Qty | G4: Type | H4: Unit | I4: Approx. Unit Price (INR) | J4: Amount (INR) | K4: Visual
A5: 1 | B5: Electromechanics and Information Technology | C5: Computer / Laptop | D5: Processor: I3, 8Gb Ram, 512Gb SSD | E5: 1 | F5: 1 | G5: Tools & Equipment | H5: unit | I5: 42000 | J5: =F5*I5 -> 42000 | K5: Click here
A6: 2 | B6: Electromechanics and Information Technology | C6: Microsoft Office | D6: Ms office for educational usage | E6: 1 | F6: 1 | G6: Other Lab Items | H6: licence | I6: 6000 | J6: =F6*I6 -> 6000 | K6: Click here
A7: 3 | B7: Electromechanics and Information Technology | C7: AutoCAD software (to be integrated in computer) | D7: AutoCAD Software for Education Purpose | E7: 1 | F7: 1 | G7: Other Lab Items | H7: Free | I7: 0 | J7: =F7*I7 -> 0 | K7: Click here
A8: 4 | B8: Electromechanics and Information Technology | C8: Battery | D8: 9-12V 2000 to 2500 mAh rechargeable battery | E8: 6 | F8: 6 | G8: Tools & Equipment | H8: pcs | I8: 450 | J8: =F8*I8 -> 2700 | K8: Click here
A9: 5 | B9: Electromechanics and Information Technology | C9: Battery Charger | D9: 9V Batter Charger | E9: 2 | F9: 2 | G9: Tools & Equipment | H9: pcs | I9: 600 | J9: =F9*I9 -> 1200 | K9: Click here
A10: 6 | B10: Electromechanics and Information Technology | C10: Power Adaptor | D10: 9v 1Ampear | E10: 6 | F10: 6 | G10: Tools & Equipment | H10: unit | I10: 200 | J10: =F10*I10 -> 1200 | K10: Click here
A11: 7 | B11: Electromechanics and Information Technology | C11: Resistor Kit | D11: One kit contains - 30 carbon film resistors of 20 different resistance values each assorted, packaged together and labelled. Values: 0Ω, 1.5Ω, 4.7Ω, 10Ω, 47Ω, 100Ω, 220Ω, 330Ω, 470Ω, 680Ω, 1kΩ, 2.2kΩ, 3.3kΩ, 4.7kΩ, 10kΩ, 22kΩ, 47kΩ, 100kΩ, 330kΩ, 1MΩ | E11: 6 | F11: 6 | G11: Consumables | H11: kit | I11: 250 | J11: =F11*I11 -> 1500 | K11: Click here
A12: 8 | B12: Electromechanics and Information Technology | C12: Capacitor Kit | D12: Values: 10pF, 22pF, 100pF, 1nF, 10nF, 100nF, 1µF, 10µF, 100µF, 1000µF | E12: 6 | F12: 6 | G12: Consumables | H12: kit | I12: 300 | J12: =F12*I12 -> 1800 | K12: Click here
A13: 9 | B13: Electromechanics and Information Technology | C13: LDR Module | D13: 5mm/12mm, Photosensitive LDR Light Sensor Module | E13: 20 | F13: 20 | G13: Tools & Equipment | H13: unit | I13: 60 | J13: =F13*I13 -> 1200 | K13: Click here
A14: 10 | B14: Electromechanics and Information Technology | C14: Active Buzzer | D14: Medium Buzzer 5 Volts | E14: 10 | F14: 10 | G14: Tools & Equipment | H14: unit | I14: 30 | J14: =F14*I14 -> 300 | K14: Click here
A15: 11 | B15: Electromechanics and Information Technology | C15: Jumper Cable | D15: Male-Male - 20 per 10 Students | E15: 80 | F15: 80 | G15: Consumables | H15: unit | I15: 5 | J15: =F15*I15 -> 400 | K15: Click here
A16: 12 | B16: Electromechanics and Information Technology | C16: Jumper Cable | D16: Male-Female - 20 per 10 Students | E16: 80 | F16: 80 | G16: Consumables | H16: unit | I16: 5 | J16: =F16*I16 -> 400 | K16: Click here
... A299: 295 | B299: Display Boards, Tables & Storage | C299: Utensil Rack | D299: Standard Size Utensil Rack to keep kitchen utensils | E299: 1 | F299: 1 | G299: Other Lab Items | H299: unit | I299: 3500 | J299: =F299*I299 -> 3500 | K299: Click here
C300: TOTAL (approx.) | J300: =SUM(J5:J299) -> 448925
A302: Prepared by - Subodh Kumar

Sheet DL-MM
A1: Delhi CBSE - Multimedia Lab
A2: Source: state/central tender lists (NSDC, Delhi CBSE skill subjects, NVS PM SHRI) - these labs are NOT part of the PSSCIVE curriculum. Prices: approximate Indian market rates (Oct 2026, incl. GST) for budget planning only, not quotations. Qty as given in the tender list (1 if blank).
A4: S.No | B4: Section | C4: Item | D4: Specification (as in tender) | E4: Qty (as in list) | F4: Qty | G4: Type | H4: Unit | I4: Approx. Unit Price (INR) | J4: Amount (INR) | K4: Visual
A5: 1 | B5: - | C5: Computer System | D5: Processor Description Intel Core i5 / AMD Ryzen 5 Processor Generation Minimum 12th Generation for Intel or equivalent (generation or series) for other Processors Graphics Type Integrated Onsite OEM Warranty 5 years Monitor Size 21.5 / 22 / 23.5 / 23.8 inches Operating System Windows 11 Professional (STF version) / Linux RAM Size 8 GB Optical Drive (Optional) DVD RW Keyboard Wired / Wireless Mouse Wired / Wireless Total SSD Capacity 512 GB Other Features • In-Built Speakers • Webcam with 720p/30fps (1280x720 pixels) or above with microphone, Integrated privacy shutter for privacy • Camera management Software - To control the brightness, contrast, sharpness as per the room lighting for better picture clarity. • Certification - Google Meet or Zoom or Microsoft Teams or Webex Certified | E5: 4 | F5: 4 | G5: Tools & Equipment | H5: pcs | I5: 45000 | J5: =F5*I5 -> 180000 | K5: Click here
A6: 2 | B6: - | C6: Anti-virus for Computer Systems | D6: Anti Ransomware, EMAIL Protection, IDS/IPS Protection, FIREWALL Protection, Advanced Device Control, Spam Protection. •Application Control – Blocklist & Safelist, Disk Encryption Management, You Tube Access Controller, Google Access Controller, Asset Management, Installed Software report and change report, Session Activity Monitoring, Data Backup. •Browsing and Phishing Protection, Vulnerability Scan, 3 rd Party App Remover, Web Filtering, Advanced Device Control, Spam Protection, Application Control – Patch Management. •Capability to encrypt USB Pen Drive contents •Solution must have the capability to manage quarantined files centrally through the management console. •Make in India (MII) compliant product with minimum 60% local content as per Meit Y notification dated 6 th December 2019 regarding guidelines for Cyber Security products under Make In India policy. •License must remain valid for at least 1 year from the date of Commissioning of respective Lab | E6: 4 | F6: 4 | G6: Tools & Equipment | H6: licence | I6: 800 | J6: =F6*I6 -> 3200 | K6: Click here
A7: 3 | B7: - | C7: Printer | D7: Print Technology -Laser Type of Printing -Mono Paper Size -A4 Print Speed (Mono) -20 PPM or higher Duplex Feature -No Network Connectivity - Optional USB Port -Yes Duty Cycle - Minimum 2000 per Month Onsite OEM Warranty - Minimum 5 years | E7: 1 | F7: 1 | G7: Tools & Equipment | H7: pcs | I7: 12000 | J7: =F7*I7 -> 12000 | K7: Click here
A8: 4 | B8: - | C8: UPS | D8: VAH - Minimum 12 Vx 7 AH Backup Time - Minimum 10 to 15 minutes Other - Warranty shall cover both UPS system and Battery Bank over 5 years Warranty Period | E8: 4 | F8: 4 | G8: Tools & Equipment | H8: pcs | I8: 3500 | J8: =F8*I8 -> 14000 | K8: Click here
A9: 5 | B9: - | C9: Internet wifi setup | D9: 4G LTE Router with 5G sim Up to 150 Mbps download speed Ethernet LAN/WAN support Long Range coverage | E9: 1 | F9: 1 | G9: Other Lab Items | H9: unit | I9: 3500 | J9: =F9*I9 -> 3500 | K9: Click here
A10: 6 | B10: - | C10: Subject Specific TLM (laminated charts) | D10: Contains: Computer Technology - Thick Laminated Chart Chart Dimensions (approx): 70 X 100 (cm) Material: Paper Category: Chart | E10: 5 | F10: 5 | G10: Other Lab Items | H10: set | I10: 1500 | J10: =F10*I10 -> 7500 | K10: Click here
A11: 7 | B11: - | C11: Classroom chairs | D11: Material-plastic, Size: 47cm x 57cm 87cm(standard),color:black | E11: 25 | F11: 25 | G11: Other Lab Items | H11: unit | I11: 700 | J11: =F11*I11 -> 17500 | K11: Click here
A12: 8 | B12: - | C12: Computer Tables | D12: Frame Material size Hollow Rectangular Section of size 50x 25x 1.6 Mm thick Frame material of foot rest hollow Rectangular section size 50 x 25 x 1.6 mm thick | E12: 4 | F12: 4 | G12: Other Lab Items | H12: pcs | I12: 8500 | J12: =F12*I12 -> 34000 | K12: Click here
C13: TOTAL (approx.) | J13: =SUM(J5:J12) -> 271700
A15: Prepared by - Subodh Kumar

Sheet DL-FMM
A1: Delhi CBSE - Financial Markets Management (FMM) Lab
A2: Source: state/central tender lists (NSDC, Delhi CBSE skill subjects, NVS PM SHRI) - these labs are NOT part of the PSSCIVE curriculum. Prices: approximate Indian market rates (Oct 2026, incl. GST) for budget planning only, not quotations. Qty as given in the tender list (1 if blank).
A4: S.No | B4: Section | C4: Item | D4: Specification (as in tender) | E4: Qty (as in list) | F4: Qty | G4: Type | H4: Unit | I4: Approx. Unit Price (INR) | J4: Amount (INR) | K4: Visual
A5: 1 | B5: - | C5: Computer Systems (Desktop Computer) | D5: Processor Description Intel Core i5 / AMD Ryzen 5 Processor Generation Minimum 12th Generation for Intel or equivalent (generation or series) for other Processors Graphics Type Integrated Onsite OEM Warranty 5 years Monitor Size 21.5 / 22 / 23.5 / 23.8 inches Operating System Windows 11 Professional (STF version) / Linux RAM Size 8 GB Optical Drive (Optional) DVD RW Keyboard Wired / Wireless Mouse Wired / Wireless Total SSD Capacity 512 GB Other Features • In-Built Speakers • Webcam with 720p/30fps (1280x720 pixels) or above with microphone, Integrated privacy shutter for privacy • Camera management Software - To control the brightness, contrast, sharpness as per the room lighting for better picture clarity. • Certification - Google Meet or Zoom or Microsoft Teams or Webex Certified | E5: 4 | F5: 4 | G5: Tools & Equipment | H5: unit | I5: 50000 | J5: =F5*I5 -> 200000 | K5: Click here
A6: 2 | B6: - | C6: Anti-virus for Computer Systems | D6: •Anti Ransomware, EMAIL Protection, IDS/IPS Protection, FIREWALL Protection, Advanced Device Control, Spam Protection. •Application Control – Blocklist & Safelist, Disk Encryption Management, You Tube Access Controller, Google Access Controller, Asset Management, Installed Software report and change report, Session Activity Monitoring, Data Backup. •Browsing and Phishing Protection, Vulnerability Scan, 3 rd Party App Remover, Web Filtering, Advanced Device Control, Spam Protection, Application Control – Patch Management. •Capability to encrypt USB Pen Drive contents •Solution must have the capability to manage quarantined files centrally through the management console. •Make in India (MII) compliant product with minimum 60% local content as per Meit Y notification dated 6 th December 2019 regarding guidelines for Cyber Security products under Make In India policy. •License must remain valid for at least 1 year from the date of Commissioning of respective Lab | E6: 4 | F6: 4 | G6: Tools & Equipment | H6: licence | I6: 800 | J6: =F6*I6 -> 3200 | K6: Click here
A7: 3 | B7: - | C7: UPS | D7: VAH - Minimum 12 Vx 7 AH Backup Time - Minimum 10 to 15 minutes Other - Warranty shall cover both UPS system and Battery Bank over 5 years Warranty Period | E7: 4 | F7: 4 | G7: Tools & Equipment | H7: pcs | I7: 3500 | J7: =F7*I7 -> 14000 | K7: Click here
A8: 4 | B8: - | C8: Printer | D8: Print Technology -Laser Type of Printing -Mono Paper Size -A4 Print Speed (Mono) -20 PPM or higher Duplex Feature -No Network Connectivity - Optional USB Port -Yes Duty Cycle - Minimum 2000 per Month Onsite OEM Warranty - Minimum 5 years | E8: 1 | F8: 1 | G8: Tools & Equipment | H8: pcs | I8: 12000 | J8: =F8*I8 -> 12000 | K8: Click here
A9: 5 | B9: - | C9: Internet wifi setup | D9: 4G LTE Router with 5G sim Up to 150 Mbps download speed Ethernet LAN/WAN support Long Range coverage | E9: 1 | F9: 1 | G9: Other Lab Items | H9: unit | I9: 3500 | J9: =F9*I9 -> 3500 | K9: Click here
A10: 6 | B10: - | C10: Subject specific TLM(Laminated Charts) | D10: Related to stock pattern(Candle stick chart) | E10: 5 | F10: 5 | G10: Other Lab Items | H10: set | I10: 1500 | J10: =F10*I10 -> 7500 | K10: Click here
A11: 7 | B11: - | C11: Classroom chairs | D11: Material-plastic, Size: 47cm x 57cm 87cm(standard),color:black | E11: 24 | F11: 24 | G11: Other Lab Items | H11: unit | I11: 700 | J11: =F11*I11 -> 16800 | K11: Click here
A12: 8 | B12: - | C12: Computer tables | D12: Frame Material size Hollow Rectangular Section of size 50x 25x 1.6 Mm thick Frame material of foot rest hollow Rectangular section size 50 x 25 x 1.6 mm thick | E12: 4 | F12: 4 | G12: Other Lab Items | H12: pcs | I12: 8500 | J12: =F12*I12 -> 34000 | K12: Click here
C13: TOTAL (approx.) | J13: =SUM(J5:J12) -> 291000
A15: Prepared by - Subodh Kumar

Sheet DL-TAX
A1: Delhi CBSE - Taxation Lab
A2: Source: state/central tender lists (NSDC, Delhi CBSE skill subjects, NVS PM SHRI) - these labs are NOT part of the PSSCIVE curriculum. Prices: approximate Indian market rates (Oct 2026, incl. GST) for budget planning only, not quotations. Qty as given in the tender list (1 if blank).
A4: S.No | B4: Section | C4: Item | D4: Specification (as in tender) | E4: Qty (as in list) | F4: Qty | G4: Type | H4: Unit | I4: Approx. Unit Price (INR) | J4: Amount (INR) | K4: Visual
A5: 1 | B5: - | C5: Computer | D5: Processor Description Intel Core i5 / AMD Ryzen 5 Processor Generation Minimum 12th Generation for Intel or equivalent (generation or series) for other Processors Graphics Type Integrated Onsite OEM Warranty 5 years Monitor Size 21.5 / 22 / 23.5 / 23.8 inches Operating System Windows 11 Professional (STF version) / Linux RAM Size 8 GB Optical Drive (Optional) DVD RW Keyboard Wired / Wireless Mouse Wired / Wireless Total SSD Capacity 512 GB Other Features • In-Built Speakers • Webcam with 720p/30fps (1280x720 pixels) or above with microphone, Integrated privacy shutter for privacy • Camera management Software - To control the brightness, contrast, sharpness as per the room lighting for better picture clarity. • Certification - Google Meet or Zoom or Microsoft Teams or Webex Certified | E5: 4 | F5: 4 | G5: Tools & Equipment | H5: pcs | I5: 45000 | J5: =F5*I5 -> 180000 | K5: Click here
A6: 2 | B6: - | C6: Anti-virus for Computer Systems | D6: •Anti Ransomware, EMAIL Protection, IDS/IPS Protection, FIREWALL Protection, Advanced Device Control, Spam Protection. •Application Control – Blocklist & Safelist, Disk Encryption Management, You Tube Access Controller, Google Access Controller, Asset Management, Installed Software report and change report, Session Activity Monitoring, Data Backup. •Browsing and Phishing Protection, Vulnerability Scan, 3 rd Party App Remover, Web Filtering, Advanced Device Control, Spam Protection, Application Control – Patch Management. •Capability to encrypt USB Pen Drive contents •Solution must have the capability to manage quarantined files centrally through the management console. •Make in India (MII) compliant product with minimum 60% local content as per Meit Y notification dated 6 th December 2019 regarding guidelines for Cyber Security products under Make In India policy. •License must remain valid for at least 1 year from the date of Commissioning of respective Lab | E6: 4 | F6: 4 | G6: Tools & Equipment | H6: licence | I6: 800 | J6: =F6*I6 -> 3200 | K6: Click here
A7: 3 | B7: - | C7: Internet wifi setup | D7: 4G LTE Router, Up to 150 Mbps download speed Ethernet LAN/WAN support,Long Range coverage | E7: 1 | F7: 1 | G7: Other Lab Items | H7: unit | I7: 3500 | J7: =F7*I7 -> 3500 | K7: Click here
A8: 4 | B8: - | C8: Printer | D8: Print Technology -Laser Type of Printing -Mono Paper Size -A4 Print Speed (Mono) -20 PPM or higher Duplex Feature -No Network Connectivity - Optional USB Port -Yes Duty Cycle - Minimum 2000 per Month Onsite OEM Warranty - Minimum 5 years | E8: 1 | F8: 1 | G8: Tools & Equipment | H8: pcs | I8: 12000 | J8: =F8*I8 -> 12000 | K8: Click here
A9: 5 | B9: - | C9: White Board | D9: 5*3 ft | E9: 1 | F9: 1 | G9: Other Lab Items | H9: pcs | I9: 3500 | J9: =F9*I9 -> 3500 | K9: Click here
A10: 6 | B10: - | C10: Projector | D10: Native Resolution 1920 x 1080 FHD Max. Supported Resolution 1080p (Max.) RAM 1 GB Quad Core Processor Storage (ROM) 8 GB Wi-Fi Connectivity Dual band Connectivity (2.4GHz & 5GHz) Bluetooth Version v5.0 Display technology LED Lamp Lifespan 50,000h Brightness 10000 Lumens | E10: 1 | F10: 1 | G10: Other Lab Items | H10: pcs | I10: 45000 | J10: =F10*I10 -> 45000 | K10: Click here
A11: 7 | B11: - | C11: UPS | D11: VAH - Minimum 12 Vx 7 AH Backup Time - Minimum 10 to 15 minutes Other - Warranty shall cover both UPS system and Battery Bank over 5 years Warranty Period | E11: 4 | F11: 4 | G11: Tools & Equipment | H11: pcs | I11: 3500 | J11: =F11*I11 -> 14000 | K11: Click here
A12: 8 | B12: - | C12: Accounting Software | D12: Tlly prime / education version | E12: 1 | F12: 1 | G12: Other Lab Items | H12: unit | I12: 18000 | J12: =F12*I12 -> 18000 | K12: Click here
A13: 9 | B13: - | C13: Tax Charts | D13: - | E13: 5 | F13: 5 | G13: Other Lab Items | H13: unit | I13: 300 | J13: =F13*I13 -> 1500 | K13: Click here
A14: 10 | B14: - | C14: Sample documentation kit | D14: - | E14: 5 | F14: 5 | G14: Consumables | H14: kit | I14: 1500 | J14: =F14*I14 -> 7500 | K14: Click here
A15: 11 | B15: - | C15: Classroom chairs | D15: Material-plastic, Size: 47cm x 57cm 87cm(standard),color:black | E15: 25 | F15: 25 | G15: Other Lab Items | H15: unit | I15: 700 | J15: =F15*I15 -> 17500 | K15: Click here
A16: 12 | B16: - | C16: Computer Tables | D16: Frame Material size Hollow Rectangular Section of size 50x 25x 1.6 Mm thick Frame material of foot rest hollow Rectangular section size 50 x 25 x 1.6 mm thick | E16: 4 | F16: 4 | G16: Other Lab Items | H16: pcs | I16: 8500 | J16: =F16*I16 -> 34000 | K16: Click here
C17: TOTAL (approx.) | J17: =SUM(J5:J16) -> 339700
A19: Prepared by - Subodh Kumar

Sheet DL-MLT
A1: Delhi CBSE - Medical Diagnostics Lab
A2: Source: state/central tender lists (NSDC, Delhi CBSE skill subjects, NVS PM SHRI) - these labs are NOT part of the PSSCIVE curriculum. Prices: approximate Indian market rates (Oct 2026, incl. GST) for budget planning only, not quotations. Qty as given in the tender list (1 if blank).
A4: S.No | B4: Section | C4: Item | D4: Specification (as in tender) | E4: Qty (as in list) | F4: Qty | G4: Type | H4: Unit | I4: Approx. Unit Price (INR) | J4: Amount (INR) | K4: Visual
A5: 1 | B5: - | C5: Registers for documentation | D5: Five separate hard-bound A4 registers, minimum 200 numbered pages each, 70 GSM or better paper, durable cover and index pages. Register formats shall cover: (i) sample/accession and rejection log, (ii) reagent and consumable stock/expiry log, (iii) equipment use, cleaning, calibration and maintenance log, (iv) refrigerator/incubator temperature and quality-control log, and (v) biomedical-waste, spill, exposure and incident log. Printing shall be clear and fields shall permit date, time, batch/lot, operator and trainer signature. | E5: 5 | F5: 5 | G5: Other Lab Items | H5: unit | I5: 350 | J5: =F5*I5 -> 1750 | K5: Click here
A6: 2 | B6: - | C6: Bio hazard bags for Waste Disposal | D6: Colour-coded, non-chlorinated, leak-resistant biomedical-waste bags suitable for foot-operated bins; yellow and red categories, assorted 30 L and 60 L sizes, minimum 50 bags per pack. Bags shall be tear resistant, have biohazard symbol and space for source/date marking, and comply with the latest Bio-Medical Waste Management Rules and applicable CPCB guidance. Each supplied unit shall be treated as one pack. | E6: 5 | F6: 5 | G6: Consumables | H6: pack of 50 | I6: 300 | J6: =F6*I6 -> 1500 | K6: Click here
A7: 3 | B7: - | C7: Staining solution / reagents / Romanowsky stains | D7: Ready-to-use Romanowsky staining set comprising Leishman stain and/or Wright-Giemsa/Giemsa stain, laboratory/IVD grade, minimum 100 mL per bottle. Reagents shall give clear nuclear and cytoplasmic differentiation on fixed peripheral-blood smear, and shall be supplied with batch/lot number, certificate of analysis, safety data sheet, storage condition and minimum 12 months residual shelf life at delivery. | E7: 5 | F7: 5 | G7: Consumables | H7: set | I7: 1200 | J7: =F7*I7 -> 6000 | K7: Click here
A8: 4 | B8: - | C8: Buffer | D8: Phosphate buffer solution/tablets for Romanowsky staining, pH 6.8 ±0.05 at 25°C. Ready-to-use pack of minimum 500 mL or tablets/powder sufficient to prepare at least 5 L with distilled water. Pack shall state preparation method, storage condition, batch number and expiry, and be supplied with certificate of analysis and safety data sheet. | E8: 1 | F8: 1 | G8: Consumables | H8: bottle | I8: 350 | J8: =F8*I8 -> 350 | K8: Click here
A9: 5 | B9: - | C9: RBC pipette | D9: Thoma-type RBC diluting pipette of uniform-bore borosilicate glass, clearly marked at 0.5, 1 and 101, with red identification bead, durable graduations and leak-free construction. Each pipette shall include a compatible mechanical aspirator/rubber tube with mouthpiece guard or pipette bulb; supply protective storage case and cleaning instructions. | E9: 30 | F9: 30 | G9: Consumables | H9: unit | I9: 250 | J9: =F9*I9 -> 7500 | K9: Click here
A10: 6 | B10: - | C10: WBC Pipette | D10: Thoma-type WBC diluting pipette of uniform-bore borosilicate glass, clearly marked at 0.5, 1 and 11, with white identification bead, durable graduations and leak-free construction. Each pipette shall include a compatible mechanical aspirator/rubber tube with mouthpiece guard or pipette bulb; supply protective storage case and cleaning instructions. | E10: 30 | F10: 30 | G10: Consumables | H10: unit | I10: 250 | J10: =F10*I10 -> 7500 | K10: Click here
A11: 7 | B11: - | C11: Pasteur Pipette | D11: Disposable low-density polyethylene transfer/Pasteur pipette, approximately 3 mL total capacity with integral bulb, clear graduations at least up to 1 mL, chemically resistant, non-pyrogenic and free from visible defects. Each supply unit shall comprise a sealed pack of minimum 100 pipettes; sterile packs shall be provided where the intended exercise requires sterility. | E11: 10 | F11: 10 | G11: Consumables | H11: piece | I11: 5 | J11: =F11*I11 -> 50 | K11: Click here
A12: 8 | B12: - | C12: Diluting fluids | D12: Ready-to-use cell-counting diluting-fluid set comprising mercury-free isotonic RBC diluent and WBC diluent equivalent to Turk’s solution, minimum 100 mL each. Fluids shall be filtered, stable and suitable for manual haemocytometer demonstration, with batch/lot number, certificate of analysis, safety data sheet, storage instructions and minimum 12 months residual shelf life. | E12: 5 | F12: 5 | G12: Consumables | H12: set | I12: 900 | J12: =F12*I12 -> 4500 | K12: Click here
A13: 9 | B13: - | C13: Glass tubes | D13: Laboratory test-tube set made of neutral borosilicate 3.3 glass, transparent, uniform wall, heat and chemical resistant, with fire-polished rim. Each set shall contain tubes in approximately 12 × 75 mm and 15 × 125 mm sizes, minimum 50 tubes of each size, suitable for repeated washing/autoclaving; tubes shall be free from cracks, chips and distortion. | E13: 15 | F13: 15 | G13: Tools & Equipment | H13: pcs | I13: 80 | J13: =F13*I13 -> 1200 | K13: Click here
A14: 10 | B14: - | C14: Urine Testing strips | D14: Multi-parameter urine reagent strips for qualitative/semi-quantitative determination of at least glucose, protein, ketone, blood, pH, specific gravity, bilirubin, urobilinogen, nitrite and leukocytes. Strips shall have distinct colour chart, reaction time not exceeding 120 seconds, desiccant-protected container, batch number and expiry; minimum 100 strips per vial and at least 12 months residual shelf life. | E14: 30 | F14: 30 | G14: Consumables | H14: strip | I14: 15 | J14: =F14*I14 -> 450 | K14: Click here
A15: 11 | B15: - | C15: Occult blood strips | D15: Single-use faecal occult blood test strip/cassette based on immunochromatographic detection of human haemoglobin, with built-in procedural control, individual foil pouch, specimen-collection tube/buffer and illustrated instructions. Kit shall be from a duly licensed manufacturer/importer where applicable, with batch number, stated analytical cut-off, storage range and minimum 12 months residual shelf life. | E15: 30 | F15: 30 | G15: Consumables | H15: test | I15: 60 | J15: =F15*I15 -> 1800 | K15: Click here
A16: 12 | B16: - | C16: Bio hazard bags for Waste Disposal / Blue sharps container for waste disposal | D16: Biomedical-waste segregation set comprising colour-coded, non-chlorinated yellow/red bags and rigid containers as applicable, plus a WHITE (translucent)—not blue—puncture-proof, leak-proof and tamper-proof sharps container with one-way opening and biohazard marking. Blue rigid container shall be used only for glassware/metal items as prescribed. Capacity approximately 5 L for sharps and 10–30 L for other containers. | E16: 5 | F16: 5 | G16: Consumables | H16: set | I16: 1500 | J16: =F16*I16 -> 7500 | K16: Click here
... A44: 40 | B44: - | C44: Tube racks / slide racks | D44: Laboratory rack set comprising: (i) autoclavable polypropylene or SS 304 test-tube rack with at least 30 holes suitable for 12–18 mm tubes, and (ii) corrosion-resistant microscope-slide staining/drying rack holding at least 30 slides. Racks shall be stable, washable, chemically resistant, clearly labelled and free from sharp edges. Each supplied unit shall contain one rack of each type. | E44: 3 | F44: 3 | G44: Other Lab Items | H44: set | I44: 1200 | J44: =F44*I44 -> 3600 | K44: Click here
C45: TOTAL (approx.) | J45: =SUM(J5:J44) -> 398250
A47: Prepared by - Subodh Kumar
