Workbook

Sheet By Job Role
A1: Lab Setup Budget - by Job Role (PSSCIVE labs + Additional NSDC / Delhi CBSE / NVS labs)
A2: Prices: approximate Indian market rates (Oct 2026, incl. GST) for budget planning only, not quotations. Quantity: as given in the PSSCIVE curriculum where available; 'per student' items assume a batch of 20; otherwise 1 unit is assumed. Additional labs (NSDC, Delhi CBSE, NVS PM SHRI - outside PSSCIVE) are listed at the end with tender-list quantities. Blue cells are inputs you can change. Prepared by - Subodh Kumar
A4: Sector | B4: Job Role | C4: QP Code | D4: Class | E4: Approved (list of 88) | F4: No. of items | G4: Tools & Equipment (INR) | H4: Other Lab Items (INR) | I4: Consumables (INR) | J4: Total (INR) | K4: Total (INR lakh)
A5: Agriculture | B5: Agriculture Extension Service Provider | C5: AGR/Q7601 | D5: XI-XII | E5: No | F5: =COUNTIFS(Data!$C$2:$C$7199,C5,Data!$D$2:$D$7199,D5) -> 4 | G5: =SUMIFS(Data!$L$2:$L$7199,Data!$C$2:$C$7199,$C5,Data!$D$2:$D$7199,$D5,Data!$F$2:$F$7199,"Tools & Equipment") -> 0 | H5: =SUMIFS(Data!$L$2:$L$7199,Data!$C$2:$C$7199,$C5,Data!$D$2:$D$7199,$D5,Data!$F$2:$F$7199,"Other Lab Items") -> 94500 | I5: =SUMIFS(Data!$L$2:$L$7199,Data!$C$2:$C$7199,$C5,Data!$D$2:$D$7199,$D5,Data!$F$2:$F$7199,"Consumables") -> 0 | J5: =SUM(G5:I5) -> 94500 | K5: =ROUND(J5/100000,2) -> 0.95
A6: Agriculture | B6: Agriculture Machinery Operator | C6: AGR/Q1103 | D6: XI-XII | E6: No | F6: =COUNTIFS(Data!$C$2:$C$7199,C6,Data!$D$2:$D$7199,D6) -> 52 | G6: =SUMIFS(Data!$L$2:$L$7199,Data!$C$2:$C$7199,$C6,Data!$D$2:$D$7199,$D6,Data!$F$2:$F$7199,"Tools & Equipment") -> 613960 | H6: =SUMIFS(Data!$L$2:$L$7199,Data!$C$2:$C$7199,$C6,Data!$D$2:$D$7199,$D6,Data!$F$2:$F$7199,"Other Lab Items") -> 0 | I6: =SUMIFS(Data!$L$2:$L$7199,Data!$C$2:$C$7199,$C6,Data!$D$2:$D$7199,$D6,Data!$F$2:$F$7199,"Consumables") -> 0 | J6: =SUM(G6:I6) -> 613960 | K6: =ROUND(J6/100000,2) -> 6.14
A7: Agriculture | B7: Animal Health Worker | C7: AGR/Q4804 | D7: IX-X | E7: No | F7: =COUNTIFS(Data!$C$2:$C$7199,C7,Data!$D$2:$D$7199,D7) -> 43 | G7: =SUMIFS(Data!$L$2:$L$7199,Data!$C$2:$C$7199,$C7,Data!$D$2:$D$7199,$D7,Data!$F$2:$F$7199,"Tools & Equipment") -> 77980 | H7: =SUMIFS(Data!$L$2:$L$7199,Data!$C$2:$C$7199,$C7,Data!$D$2:$D$7199,$D7,Data!$F$2:$F$7199,"Other Lab Items") -> 102100 | I7: =SUMIFS(Data!$L$2:$L$7199,Data!$C$2:$C$7199,$C7,Data!$D$2:$D$7199,$D7,Data!$F$2:$F$7199,"Consumables") -> 1820 | J7: =SUM(G7:I7) -> 181900 | K7: =ROUND(J7/100000,2) -> 1.82
A8: Agriculture | B8: Bamboo Grower | C8: AGR/Q6101 | D8: IX-X | E8: No | F8: =COUNTIFS(Data!$C$2:$C$7199,C8,Data!$D$2:$D$7199,D8) -> 21 | G8: =SUMIFS(Data!$L$2:$L$7199,Data!$C$2:$C$7199,$C8,Data!$D$2:$D$7199,$D8,Data!$F$2:$F$7199,"Tools & Equipment") -> 44150 | H8: =SUMIFS(Data!$L$2:$L$7199,Data!$C$2:$C$7199,$C8,Data!$D$2:$D$7199,$D8,Data!$F$2:$F$7199,"Other Lab Items") -> 0 | I8: =SUMIFS(Data!$L$2:$L$7199,Data!$C$2:$C$7199,$C8,Data!$D$2:$D$7199,$D8,Data!$F$2:$F$7199,"Consumables") -> 370 | J8: =SUM(G8:I8) -> 44520 | K8: =ROUND(J8/100000,2) -> 0.45
A9: Agriculture | B9: Cereal Crop Grower | C9: AGR/Q0105 | D9: IX-X | E9: No | F9: =COUNTIFS(Data!$C$2:$C$7199,C9,Data!$D$2:$D$7199,D9) -> 26 | G9: =SUMIFS(Data!$L$2:$L$7199,Data!$C$2:$C$7199,$C9,Data!$D$2:$D$7199,$D9,Data!$F$2:$F$7199,"Tools & Equipment") -> 110000 | H9: =SUMIFS(Data!$L$2:$L$7199,Data!$C$2:$C$7199,$C9,Data!$D$2:$D$7199,$D9,Data!$F$2:$F$7199,"Other Lab Items") -> 0 | I9: =SUMIFS(Data!$L$2:$L$7199,Data!$C$2:$C$7199,$C9,Data!$D$2:$D$7199,$D9,Data!$F$2:$F$7199,"Consumables") -> 873 | J9: =SUM(G9:I9) -> 110873 | K9: =ROUND(J9/100000,2) -> 1.11
A10: Agriculture | B10: Citrus Fruit Grower | C10: AGR/Q0303 | D10: IX-X | E10: No | F10: =COUNTIFS(Data!$C$2:$C$7199,C10,Data!$D$2:$D$7199,D10) -> 66 | G10: =SUMIFS(Data!$L$2:$L$7199,Data!$C$2:$C$7199,$C10,Data!$D$2:$D$7199,$D10,Data!$F$2:$F$7199,"Tools & Equipment") -> 570690 | H10: =SUMIFS(Data!$L$2:$L$7199,Data!$C$2:$C$7199,$C10,Data!$D$2:$D$7199,$D10,Data!$F$2:$F$7199,"Other Lab Items") -> 250 | I10: =SUMIFS(Data!$L$2:$L$7199,Data!$C$2:$C$7199,$C10,Data!$D$2:$D$7199,$D10,Data!$F$2:$F$7199,"Consumables") -> 873 | J10: =SUM(G10:I10) -> 571813 | K10: =ROUND(J10/100000,2) -> 5.72
A11: Agriculture | B11: Dairy Farmer/ Entrepreneur | C11: AGR/Q4101 | D11: XI-XII | E11: Yes | F11: =COUNTIFS(Data!$C$2:$C$7199,C11,Data!$D$2:$D$7199,D11) -> 43 | G11: =SUMIFS(Data!$L$2:$L$7199,Data!$C$2:$C$7199,$C11,Data!$D$2:$D$7199,$D11,Data!$F$2:$F$7199,"Tools & Equipment") -> 77380 | H11: =SUMIFS(Data!$L$2:$L$7199,Data!$C$2:$C$7199,$C11,Data!$D$2:$D$7199,$D11,Data!$F$2:$F$7199,"Other Lab Items") -> 102100 | I11: =SUMIFS(Data!$L$2:$L$7199,Data!$C$2:$C$7199,$C11,Data!$D$2:$D$7199,$D11,Data!$F$2:$F$7199,"Consumables") -> 1820 | J11: =SUM(G11:I11) -> 181300 | K11: =ROUND(J11/100000,2) -> 1.81
A12: Agriculture | B12: Dairy Worker | C12: AGR/Q4102 | D12: IX-X | E12: Yes | F12: =COUNTIFS(Data!$C$2:$C$7199,C12,Data!$D$2:$D$7199,D12) -> 42 | G12: =SUMIFS(Data!$L$2:$L$7199,Data!$C$2:$C$7199,$C12,Data!$D$2:$D$7199,$D12,Data!$F$2:$F$7199,"Tools & Equipment") -> 77260 | H12: =SUMIFS(Data!$L$2:$L$7199,Data!$C$2:$C$7199,$C12,Data!$D$2:$D$7199,$D12,Data!$F$2:$F$7199,"Other Lab Items") -> 102100 | I12: =SUMIFS(Data!$L$2:$L$7199,Data!$C$2:$C$7199,$C12,Data!$D$2:$D$7199,$D12,Data!$F$2:$F$7199,"Consumables") -> 2810 | J12: =SUM(G12:I12) -> 182170 | K12: =ROUND(J12/100000,2) -> 1.82
A13: Agriculture | B13: Fish Seed Grower | C13: AGR/Q4908 | D13: XI-XII | E13: No | F13: =COUNTIFS(Data!$C$2:$C$7199,C13,Data!$D$2:$D$7199,D13) -> 28 | G13: =SUMIFS(Data!$L$2:$L$7199,Data!$C$2:$C$7199,$C13,Data!$D$2:$D$7199,$D13,Data!$F$2:$F$7199,"Tools & Equipment") -> 83150 | H13: =SUMIFS(Data!$L$2:$L$7199,Data!$C$2:$C$7199,$C13,Data!$D$2:$D$7199,$D13,Data!$F$2:$F$7199,"Other Lab Items") -> 1750 | I13: =SUMIFS(Data!$L$2:$L$7199,Data!$C$2:$C$7199,$C13,Data!$D$2:$D$7199,$D13,Data!$F$2:$F$7199,"Consumables") -> 1050 | J13: =SUM(G13:I13) -> 85950 | K13: =ROUND(J13/100000,2) -> 0.86
A14: Agriculture | B14: Floriculturist (Open Cultivation) | C14: AGR/Q0701 | D14: XI-XII | E14: Yes | F14: =COUNTIFS(Data!$C$2:$C$7199,C14,Data!$D$2:$D$7199,D14) -> 70 | G14: =SUMIFS(Data!$L$2:$L$7199,Data!$C$2:$C$7199,$C14,Data!$D$2:$D$7199,$D14,Data!$F$2:$F$7199,"Tools & Equipment") -> 115250 | H14: =SUMIFS(Data!$L$2:$L$7199,Data!$C$2:$C$7199,$C14,Data!$D$2:$D$7199,$D14,Data!$F$2:$F$7199,"Other Lab Items") -> 0 | I14: =SUMIFS(Data!$L$2:$L$7199,Data!$C$2:$C$7199,$C14,Data!$D$2:$D$7199,$D14,Data!$F$2:$F$7199,"Consumables") -> 3598 | J14: =SUM(G14:I14) -> 118848 | K14: =ROUND(J14/100000,2) -> 1.19
A15: Agriculture | B15: Floriculturist - Protected Cultivation | C15: AGR/Q0702 | D15: XI-XII | E15: No | F15: =COUNTIFS(Data!$C$2:$C$7199,C15,Data!$D$2:$D$7199,D15) -> 68 | G15: =SUMIFS(Data!$L$2:$L$7199,Data!$C$2:$C$7199,$C15,Data!$D$2:$D$7199,$D15,Data!$F$2:$F$7199,"Tools & Equipment") -> 644040 | H15: =SUMIFS(Data!$L$2:$L$7199,Data!$C$2:$C$7199,$C15,Data!$D$2:$D$7199,$D15,Data!$F$2:$F$7199,"Other Lab Items") -> 24000 | I15: =SUMIFS(Data!$L$2:$L$7199,Data!$C$2:$C$7199,$C15,Data!$D$2:$D$7199,$D15,Data!$F$2:$F$7199,"Consumables") -> 2055 | J15: =SUM(G15:I15) -> 670095 | K15: =ROUND(J15/100000,2) -> 6.7
A16: Agriculture | B16: Gardener | C16: AGR/Q0801 | D16: XI-XII | E16: Yes | F16: =COUNTIFS(Data!$C$2:$C$7199,C16,Data!$D$2:$D$7199,D16) -> 33 | G16: =SUMIFS(Data!$L$2:$L$7199,Data!$C$2:$C$7199,$C16,Data!$D$2:$D$7199,$D16,Data!$F$2:$F$7199,"Tools & Equipment") -> 155520 | H16: =SUMIFS(Data!$L$2:$L$7199,Data!$C$2:$C$7199,$C16,Data!$D$2:$D$7199,$D16,Data!$F$2:$F$7199,"Other Lab Items") -> 250 | I16: =SUMIFS(Data!$L$2:$L$7199,Data!$C$2:$C$7199,$C16,Data!$D$2:$D$7199,$D16,Data!$F$2:$F$7199,"Consumables") -> 358 | J16: =SUM(G16:I16) -> 156128 | K16: =ROUND(J16/100000,2) -> 1.56
... A177: NVS PM SHRI (Additional Labs) | B177: Multi-Skill Lab | C177: NVS-MSL | D177: School | E177: - | F177: =COUNTIFS(Data!$C$2:$C$7199,C177,Data!$D$2:$D$7199,D177) -> 295 | G177: =SUMIFS(Data!$L$2:$L$7199,Data!$C$2:$C$7199,$C177,Data!$D$2:$D$7199,$D177,Data!$F$2:$F$7199,"Tools & Equipment") -> 320670 | H177: =SUMIFS(Data!$L$2:$L$7199,Data!$C$2:$C$7199,$C177,Data!$D$2:$D$7199,$D177,Data!$F$2:$F$7199,"Other Lab Items") -> 108850 | I177: =SUMIFS(Data!$L$2:$L$7199,Data!$C$2:$C$7199,$C177,Data!$D$2:$D$7199,$D177,Data!$F$2:$F$7199,"Consumables") -> 19405 | J177: =SUM(G177:I177) -> 448925 | K177: =ROUND(J177/100000,2) -> 4.49
A178: GRAND TOTAL | F178: =SUM(F5:F177) -> 7198 | G178: =SUM(G5:G177) -> 79708380 | H178: =SUM(H5:H177) -> 57306515 | I178: =SUM(I5:I177) -> 1296579 | J178: =SUM(J5:J177) -> 138311474 | K178: =ROUND(J178/100000,2) -> 1383.11

Sheet By Sector
A1: Lab Setup Budget - by Sector
A2: Prices: approximate Indian market rates (Oct 2026, incl. GST) for budget planning only, not quotations. Quantity: as given in the PSSCIVE curriculum where available; 'per student' items assume a batch of 20; otherwise 1 unit is assumed. Additional labs (NSDC, Delhi CBSE, NVS PM SHRI - outside PSSCIVE) are listed at the end with tender-list quantities. Blue cells are inputs you can change. Prepared by - Subodh Kumar
A4: Sector | B4: Job roles | C4: Tools & Equipment (INR) | D4: Other Lab Items (INR) | E4: Consumables (INR) | F4: Total for all roles (INR) | G4: Average per role (INR lakh)
A5: Agriculture | B5: =COUNTIF('By Job Role'!$A$5:$A$177,A5) -> 24 | C5: =SUMIF('By Job Role'!$A$5:$A$177,A5,'By Job Role'!$G$5:$G$177) -> 8338590 | D5: =SUMIF('By Job Role'!$A$5:$A$177,A5,'By Job Role'!$H$5:$H$177) -> 949490 | E5: =SUMIF('By Job Role'!$A$5:$A$177,A5,'By Job Role'!$I$5:$I$177) -> 280027 | F5: =SUMIF('By Job Role'!$A$5:$A$177,A5,'By Job Role'!$J$5:$J$177) -> 9568107 | G5: =IF(B5=0,0,ROUND(F5/B5/100000,2)) -> 3.99
A6: Aerospace & Aviation | B6: =COUNTIF('By Job Role'!$A$5:$A$177,A6) -> 1 | C6: =SUMIF('By Job Role'!$A$5:$A$177,A6,'By Job Role'!$G$5:$G$177) -> 975850 | D6: =SUMIF('By Job Role'!$A$5:$A$177,A6,'By Job Role'!$H$5:$H$177) -> 145000 | E6: =SUMIF('By Job Role'!$A$5:$A$177,A6,'By Job Role'!$I$5:$I$177) -> 251000 | F6: =SUMIF('By Job Role'!$A$5:$A$177,A6,'By Job Role'!$J$5:$J$177) -> 1371850 | G6: =IF(B6=0,0,ROUND(F6/B6/100000,2)) -> 13.72
A7: Apparel | B7: =COUNTIF('By Job Role'!$A$5:$A$177,A7) -> 12 | C7: =SUMIF('By Job Role'!$A$5:$A$177,A7,'By Job Role'!$G$5:$G$177) -> 5085770 | D7: =SUMIF('By Job Role'!$A$5:$A$177,A7,'By Job Role'!$H$5:$H$177) -> 1235780 | E7: =SUMIF('By Job Role'!$A$5:$A$177,A7,'By Job Role'!$I$5:$I$177) -> 43610 | F7: =SUMIF('By Job Role'!$A$5:$A$177,A7,'By Job Role'!$J$5:$J$177) -> 6365160 | G7: =IF(B7=0,0,ROUND(F7/B7/100000,2)) -> 5.3
A8: Automotive | B8: =COUNTIF('By Job Role'!$A$5:$A$177,A8) -> 6 | C8: =SUMIF('By Job Role'!$A$5:$A$177,A8,'By Job Role'!$G$5:$G$177) -> 7769080 | D8: =SUMIF('By Job Role'!$A$5:$A$177,A8,'By Job Role'!$H$5:$H$177) -> 8699050 | E8: =SUMIF('By Job Role'!$A$5:$A$177,A8,'By Job Role'!$I$5:$I$177) -> 23485 | F8: =SUMIF('By Job Role'!$A$5:$A$177,A8,'By Job Role'!$J$5:$J$177) -> 16491615 | G8: =IF(B8=0,0,ROUND(F8/B8/100000,2)) -> 27.49
A9: BFSI | B9: =COUNTIF('By Job Role'!$A$5:$A$177,A9) -> 6 | C9: =SUMIF('By Job Role'!$A$5:$A$177,A9,'By Job Role'!$G$5:$G$177) -> 40300 | D9: =SUMIF('By Job Role'!$A$5:$A$177,A9,'By Job Role'!$H$5:$H$177) -> 2065270 | E9: =SUMIF('By Job Role'!$A$5:$A$177,A9,'By Job Role'!$I$5:$I$177) -> 3290 | F9: =SUMIF('By Job Role'!$A$5:$A$177,A9,'By Job Role'!$J$5:$J$177) -> 2108860 | G9: =IF(B9=0,0,ROUND(F9/B9/100000,2)) -> 3.51
A10: Beauty & Wellness | B10: =COUNTIF('By Job Role'!$A$5:$A$177,A10) -> 6 | C10: =SUMIF('By Job Role'!$A$5:$A$177,A10,'By Job Role'!$G$5:$G$177) -> 704990 | D10: =SUMIF('By Job Role'!$A$5:$A$177,A10,'By Job Role'!$H$5:$H$177) -> 884820 | E10: =SUMIF('By Job Role'!$A$5:$A$177,A10,'By Job Role'!$I$5:$I$177) -> 7210 | F10: =SUMIF('By Job Role'!$A$5:$A$177,A10,'By Job Role'!$J$5:$J$177) -> 1597020 | G10: =IF(B10=0,0,ROUND(F10/B10/100000,2)) -> 2.66
A11: Capital Goods | B11: =COUNTIF('By Job Role'!$A$5:$A$177,A11) -> 1 | C11: =SUMIF('By Job Role'!$A$5:$A$177,A11,'By Job Role'!$G$5:$G$177) -> 71260 | D11: =SUMIF('By Job Role'!$A$5:$A$177,A11,'By Job Role'!$H$5:$H$177) -> 316500 | E11: =SUMIF('By Job Role'!$A$5:$A$177,A11,'By Job Role'!$I$5:$I$177) -> 900 | F11: =SUMIF('By Job Role'!$A$5:$A$177,A11,'By Job Role'!$J$5:$J$177) -> 388660 | G11: =IF(B11=0,0,ROUND(F11/B11/100000,2)) -> 3.89
A12: Construction | B12: =COUNTIF('By Job Role'!$A$5:$A$177,A12) -> 5 | C12: =SUMIF('By Job Role'!$A$5:$A$177,A12,'By Job Role'!$G$5:$G$177) -> 353170 | D12: =SUMIF('By Job Role'!$A$5:$A$177,A12,'By Job Role'!$H$5:$H$177) -> 475655 | E12: =SUMIF('By Job Role'!$A$5:$A$177,A12,'By Job Role'!$I$5:$I$177) -> 4562 | F12: =SUMIF('By Job Role'!$A$5:$A$177,A12,'By Job Role'!$J$5:$J$177) -> 833387 | G12: =IF(B12=0,0,ROUND(F12/B12/100000,2)) -> 1.67
A13: Electronics | B13: =COUNTIF('By Job Role'!$A$5:$A$177,A13) -> 10 | C13: =SUMIF('By Job Role'!$A$5:$A$177,A13,'By Job Role'!$G$5:$G$177) -> 1330270 | D13: =SUMIF('By Job Role'!$A$5:$A$177,A13,'By Job Role'!$H$5:$H$177) -> 1550285 | E13: =SUMIF('By Job Role'!$A$5:$A$177,A13,'By Job Role'!$I$5:$I$177) -> 18860 | F13: =SUMIF('By Job Role'!$A$5:$A$177,A13,'By Job Role'!$J$5:$J$177) -> 2899415 | G13: =IF(B13=0,0,ROUND(F13/B13/100000,2)) -> 2.9
A14: Food Processing | B14: =COUNTIF('By Job Role'!$A$5:$A$177,A14) -> 8 | C14: =SUMIF('By Job Role'!$A$5:$A$177,A14,'By Job Role'!$G$5:$G$177) -> 10341530 | D14: =SUMIF('By Job Role'!$A$5:$A$177,A14,'By Job Role'!$H$5:$H$177) -> 101450 | E14: =SUMIF('By Job Role'!$A$5:$A$177,A14,'By Job Role'!$I$5:$I$177) -> 2950 | F14: =SUMIF('By Job Role'!$A$5:$A$177,A14,'By Job Role'!$J$5:$J$177) -> 10445930 | G14: =IF(B14=0,0,ROUND(F14/B14/100000,2)) -> 13.06
A15: Green Jobs | B15: =COUNTIF('By Job Role'!$A$5:$A$177,A15) -> 5 | C15: =SUMIF('By Job Role'!$A$5:$A$177,A15,'By Job Role'!$G$5:$G$177) -> 2794760 | D15: =SUMIF('By Job Role'!$A$5:$A$177,A15,'By Job Role'!$H$5:$H$177) -> 503150 | E15: =SUMIF('By Job Role'!$A$5:$A$177,A15,'By Job Role'!$I$5:$I$177) -> 56775 | F15: =SUMIF('By Job Role'!$A$5:$A$177,A15,'By Job Role'!$J$5:$J$177) -> 3354685 | G15: =IF(B15=0,0,ROUND(F15/B15/100000,2)) -> 6.71
A16: Handicrafts & Carpet | B16: =COUNTIF('By Job Role'!$A$5:$A$177,A16) -> 4 | C16: =SUMIF('By Job Role'!$A$5:$A$177,A16,'By Job Role'!$G$5:$G$177) -> 9492100 | D16: =SUMIF('By Job Role'!$A$5:$A$177,A16,'By Job Role'!$H$5:$H$177) -> 1492900 | E16: =SUMIF('By Job Role'!$A$5:$A$177,A16,'By Job Role'!$I$5:$I$177) -> 126535 | F16: =SUMIF('By Job Role'!$A$5:$A$177,A16,'By Job Role'!$J$5:$J$177) -> 11111535 | G16: =IF(B16=0,0,ROUND(F16/B16/100000,2)) -> 27.78
... A33: NVS PM SHRI (Additional Labs) | B33: =COUNTIF('By Job Role'!$A$5:$A$177,A33) -> 1 | C33: =SUMIF('By Job Role'!$A$5:$A$177,A33,'By Job Role'!$G$5:$G$177) -> 320670 | D33: =SUMIF('By Job Role'!$A$5:$A$177,A33,'By Job Role'!$H$5:$H$177) -> 108850 | E33: =SUMIF('By Job Role'!$A$5:$A$177,A33,'By Job Role'!$I$5:$I$177) -> 19405 | F33: =SUMIF('By Job Role'!$A$5:$A$177,A33,'By Job Role'!$J$5:$J$177) -> 448925 | G33: =IF(B33=0,0,ROUND(F33/B33/100000,2)) -> 4.49
A34: GRAND TOTAL | B34: =SUM(B5:B33) -> 173 | C34: =SUM(C5:C33) -> 79708380 | D34: =SUM(D5:D33) -> 57306515 | E34: =SUM(E5:E33) -> 1296579 | F34: =SUM(F5:F33) -> 138311474

Sheet Top 20 Costliest Labs
A1: Top 20 costliest labs (by total)
A2: Prices: approximate Indian market rates (Oct 2026, incl. GST) for budget planning only, not quotations. Quantity: as given in the PSSCIVE curriculum where available; 'per student' items assume a batch of 20; otherwise 1 unit is assumed. Additional labs (NSDC, Delhi CBSE, NVS PM SHRI - outside PSSCIVE) are listed at the end with tender-list quantities. Blue cells are inputs you can change. Prepared by - Subodh Kumar
A4: Rank | B4: Job Role | C4: Sector | D4: Class | E4: Total (INR) | F4: Total (INR lakh)
A5: 1 | B5: =INDEX('By Job Role'!$B$5:$B$177,MATCH(E5,'By Job Role'!$J$5:$J$177,0)) -> Auto Electrical Design Technician | C5: =INDEX('By Job Role'!$A$5:$A$177,MATCH(E5,'By Job Role'!$J$5:$J$177,0)) -> Automotive | D5: =INDEX('By Job Role'!$D$5:$D$177,MATCH(E5,'By Job Role'!$J$5:$J$177,0)) -> XI-XII | E5: =LARGE('By Job Role'!$J$5:$J$177,A5) -> 6389130 | F5: =ROUND(E5/100000,2) -> 63.89
A6: 2 | B6: =INDEX('By Job Role'!$B$5:$B$177,MATCH(E6,'By Job Role'!$J$5:$J$177,0)) -> Bamboo Work Artisan | C6: =INDEX('By Job Role'!$A$5:$A$177,MATCH(E6,'By Job Role'!$J$5:$J$177,0)) -> Handicrafts & Carpet | D6: =INDEX('By Job Role'!$D$5:$D$177,MATCH(E6,'By Job Role'!$J$5:$J$177,0)) -> XI-XII | E6: =LARGE('By Job Role'!$J$5:$J$177,A6) -> 4760950 | F6: =ROUND(E6/100000,2) -> 47.61
A7: 3 | B7: =INDEX('By Job Role'!$B$5:$B$177,MATCH(E7,'By Job Role'!$J$5:$J$177,0)) -> Finisher and packer | C7: =INDEX('By Job Role'!$A$5:$A$177,MATCH(E7,'By Job Role'!$J$5:$J$177,0)) -> Apparel | D7: =INDEX('By Job Role'!$D$5:$D$177,MATCH(E7,'By Job Role'!$J$5:$J$177,0)) -> XI-XII | E7: =LARGE('By Job Role'!$J$5:$J$177,A7) -> 4172815 | F7: =ROUND(E7/100000,2) -> 41.73
A8: 4 | B8: =INDEX('By Job Role'!$B$5:$B$177,MATCH(E8,'By Job Role'!$J$5:$J$177,0)) -> Warehouse Associate | C8: =INDEX('By Job Role'!$A$5:$A$177,MATCH(E8,'By Job Role'!$J$5:$J$177,0)) -> Logistics | D8: =INDEX('By Job Role'!$D$5:$D$177,MATCH(E8,'By Job Role'!$J$5:$J$177,0)) -> IX-X | E8: =LARGE('By Job Role'!$J$5:$J$177,A8) -> 4028725 | F8: =ROUND(E8/100000,2) -> 40.29
A9: 5 | B9: =INDEX('By Job Role'!$B$5:$B$177,MATCH(E9,'By Job Role'!$J$5:$J$177,0)) -> Warehouse Associate | C9: =INDEX('By Job Role'!$A$5:$A$177,MATCH(E9,'By Job Role'!$J$5:$J$177,0)) -> Logistics | D9: =INDEX('By Job Role'!$D$5:$D$177,MATCH(E9,'By Job Role'!$J$5:$J$177,0)) -> IX-X | E9: =LARGE('By Job Role'!$J$5:$J$177,A9) -> 4028725 | F9: =ROUND(E9/100000,2) -> 40.29
A10: 6 | B10: =INDEX('By Job Role'!$B$5:$B$177,MATCH(E10,'By Job Role'!$J$5:$J$177,0)) -> Warehouse Binner | C10: =INDEX('By Job Role'!$A$5:$A$177,MATCH(E10,'By Job Role'!$J$5:$J$177,0)) -> Logistics | D10: =INDEX('By Job Role'!$D$5:$D$177,MATCH(E10,'By Job Role'!$J$5:$J$177,0)) -> IX-X | E10: =LARGE('By Job Role'!$J$5:$J$177,A10) -> 3696450 | F10: =ROUND(E10/100000,2) -> 36.96
A11: 7 | B11: =INDEX('By Job Role'!$B$5:$B$177,MATCH(E11,'By Job Role'!$J$5:$J$177,0)) -> Electric Vehicle Service Assistant | C11: =INDEX('By Job Role'!$A$5:$A$177,MATCH(E11,'By Job Role'!$J$5:$J$177,0)) -> Automotive | D11: =INDEX('By Job Role'!$D$5:$D$177,MATCH(E11,'By Job Role'!$J$5:$J$177,0)) -> IX-X | E11: =LARGE('By Job Role'!$J$5:$J$177,A11) -> 3666625 | F11: =ROUND(E11/100000,2) -> 36.67
A12: 8 | B12: =INDEX('By Job Role'!$B$5:$B$177,MATCH(E12,'By Job Role'!$J$5:$J$177,0)) -> Jute Products Artisan | C12: =INDEX('By Job Role'!$A$5:$A$177,MATCH(E12,'By Job Role'!$J$5:$J$177,0)) -> Handicrafts & Carpet | D12: =INDEX('By Job Role'!$D$5:$D$177,MATCH(E12,'By Job Role'!$J$5:$J$177,0)) -> XI-XII | E12: =LARGE('By Job Role'!$J$5:$J$177,A12) -> 3658575 | F12: =ROUND(E12/100000,2) -> 36.59
A13: 9 | B13: =INDEX('By Job Role'!$B$5:$B$177,MATCH(E13,'By Job Role'!$J$5:$J$177,0)) -> Auto Service Technician (Two and Three Wheeler) | C13: =INDEX('By Job Role'!$A$5:$A$177,MATCH(E13,'By Job Role'!$J$5:$J$177,0)) -> Automotive | D13: =INDEX('By Job Role'!$D$5:$D$177,MATCH(E13,'By Job Role'!$J$5:$J$177,0)) -> XI-XII | E13: =LARGE('By Job Role'!$J$5:$J$177,A13) -> 3384705 | F13: =ROUND(E13/100000,2) -> 33.85
A14: 10 | B14: =INDEX('By Job Role'!$B$5:$B$177,MATCH(E14,'By Job Role'!$J$5:$J$177,0)) -> Animator | C14: =INDEX('By Job Role'!$A$5:$A$177,MATCH(E14,'By Job Role'!$J$5:$J$177,0)) -> Media & Entertainment | D14: =INDEX('By Job Role'!$D$5:$D$177,MATCH(E14,'By Job Role'!$J$5:$J$177,0)) -> XI-XII | E14: =LARGE('By Job Role'!$J$5:$J$177,A14) -> 3374800 | F14: =ROUND(E14/100000,2) -> 33.75
A15: 11 | B15: =INDEX('By Job Role'!$B$5:$B$177,MATCH(E15,'By Job Role'!$J$5:$J$177,0)) -> Millet Product Processor | C15: =INDEX('By Job Role'!$A$5:$A$177,MATCH(E15,'By Job Role'!$J$5:$J$177,0)) -> Food Processing | D15: =INDEX('By Job Role'!$D$5:$D$177,MATCH(E15,'By Job Role'!$J$5:$J$177,0)) -> IX-X | E15: =LARGE('By Job Role'!$J$5:$J$177,A15) -> 2890050 | F15: =ROUND(E15/100000,2) -> 28.9
A16: 12 | B16: =INDEX('By Job Role'!$B$5:$B$177,MATCH(E16,'By Job Role'!$J$5:$J$177,0)) -> Office Executive | C16: =INDEX('By Job Role'!$A$5:$A$177,MATCH(E16,'By Job Role'!$J$5:$J$177,0)) -> Management & Entrepreneurship | D16: =INDEX('By Job Role'!$D$5:$D$177,MATCH(E16,'By Job Role'!$J$5:$J$177,0)) -> XI-XII | E16: =LARGE('By Job Role'!$J$5:$J$177,A16) -> 2485250 | F16: =ROUND(E16/100000,2) -> 24.85
... A24: 20 | B24: =INDEX('By Job Role'!$B$5:$B$177,MATCH(E24,'By Job Role'!$J$5:$J$177,0)) -> Artificial Intelligence Assistant | C24: =INDEX('By Job Role'!$A$5:$A$177,MATCH(E24,'By Job Role'!$J$5:$J$177,0)) -> IT-ITeS | D24: =INDEX('By Job Role'!$D$5:$D$177,MATCH(E24,'By Job Role'!$J$5:$J$177,0)) -> IX-X | E24: =LARGE('By Job Role'!$J$5:$J$177,A24) -> 2034725 | F24: =ROUND(E24/100000,2) -> 20.35

Sheet Data
A1: Sector | B1: Job Role | C1: QP Code | D1: Class | E1: Item | F1: Type | G1: Item ID | H1: Qty (planning) | I1: Qty basis | J1: Unit | K1: Price (INR) | L1: Amount (INR) | M1: Visual
A2: Agriculture | B2: Animal Health Worker | C2: AGR/Q4804 | D2: IX-X | E2: Burdizzo castrator | F2: Tools & Equipment | G2: P1765 | H2: 1 | I2: assumed 1 | J2: pcs | K2: 8500 | L2: =H2*K2 -> 8500 | M2: Click here
A3: Agriculture | B3: Animal Health Worker | C3: AGR/Q4804 | D3: IX-X | E3: Tagging set | F3: Tools & Equipment | G3: P2985 | H3: 1 | I3: assumed 1 | J3: kit | K3: 1200 | L3: =H3*K3 -> 1200 | M3: Click here
A4: Agriculture | B4: Animal Health Worker | C4: AGR/Q4804 | D4: IX-X | E4: Tattooing set | F4: Tools & Equipment | G4: P2997 | H4: 1 | I4: assumed 1 | J4: set | K4: 1800 | L4: =H4*K4 -> 1800 | M4: Click here
A5: Agriculture | B5: Animal Health Worker | C5: AGR/Q4804 | D5: IX-X | E5: Branding numbers | F5: Tools & Equipment | G5: P1744 | H5: 1 | I5: assumed 1 | J5: pcs | K5: 850 | L5: =H5*K5 -> 850 | M5: Click here
A6: Agriculture | B6: Animal Health Worker | C6: AGR/Q4804 | D6: IX-X | E6: Drenching bottles | F6: Tools & Equipment | G6: P1971 | H6: 1 | I6: assumed 1 | J6: pcs | K6: 450 | L6: =H6*K6 -> 450 | M6: Click here
A7: Agriculture | B7: Animal Health Worker | C7: AGR/Q4804 | D7: IX-X | E7: Mouth gags | F7: Tools & Equipment | G7: P2484 | H7: 1 | I7: assumed 1 | J7: pcs | K7: 850 | L7: =H7*K7 -> 850 | M7: Click here
A8: Agriculture | B8: Animal Health Worker | C8: AGR/Q4804 | D8: IX-X | E8: Muzzle | F8: Tools & Equipment | G8: P2494 | H8: 1 | I8: assumed 1 | J8: pcs | K8: 650 | L8: =H8*K8 -> 650 | M8: Click here
A9: Agriculture | B9: Animal Health Worker | C9: AGR/Q4804 | D9: IX-X | E9: Hoof trimmer | F9: Tools & Equipment | G9: P2249 | H9: 1 | I9: assumed 1 | J9: pcs | K9: 4500 | L9: =H9*K9 -> 4500 | M9: Click here
A10: Agriculture | B10: Animal Health Worker | C10: AGR/Q4804 | D10: IX-X | E10: Ropes | F10: Tools & Equipment | G10: P2723 | H10: 1 | I10: assumed 1 | J10: m | K10: 120 | L10: =H10*K10 -> 120 | M10: Click here
A11: Agriculture | B11: Animal Health Worker | C11: AGR/Q4804 | D11: IX-X | E11: Metal chains | F11: Tools & Equipment | G11: P2434 | H11: 1 | I11: assumed 1 | J11: kg | K11: 250 | L11: =H11*K11 -> 250 | M11: Click here
A12: Agriculture | B12: Animal Health Worker | C12: AGR/Q4804 | D12: IX-X | E12: Bull nose ring | F12: Tools & Equipment | G12: P1764 | H12: 1 | I12: assumed 1 | J12: pcs | K12: 450 | L12: =H12*K12 -> 450 | M12: Click here
A13: Agriculture | B13: Animal Health Worker | C13: AGR/Q4804 | D13: IX-X | E13: Bull nose punch | F13: Tools & Equipment | G13: P1763 | H13: 1 | I13: assumed 1 | J13: pcs | K13: 450 | L13: =H13*K13 -> 450 | M13: Click here
... A7199: NVS PM SHRI (Additional Labs) | B7199: Multi-Skill Lab | C7199: NVS-MSL | D7199: School | E7199: Utensil Rack | F7199: Other Lab Items | G7199: X234 | H7199: 1 | I7199: as in tender list | J7199: unit | K7199: 3500 | L7199: =H7199*K7199 -> 3500 | M7199: Click here
